{
	"$schema": "../.schema/species.json",
	"version": "351.6.1667004673",
	"format": "4",
	"mod": {
		"id": "1652120435",
		"tag": "AtlasPort",
		"title": "Shad's Atlas Imports"
	},
	"species": [
		{
			"name": "Luminous Anglerfish",
			"bp": "/Game/Mods/AtlasPort/Critter/Angler/AAngler_Character_BP.AAngler_Character_BP_C",
			"dinoNameTag": "Angler",
			"customTag": "Angler",
			"targetingTeamName": "Carnivore_Water",
			"mass": 300,
			"dragWeight": 250,
			"flags": [
				"canBeDragged",
				"canDrag",
				"isCarnivore",
				"isWaterDino",
				"dieIfLeftWater",
				"isTameable",
				"canBeWildTrappedWithFishBasket",
				"canBeTamedWithFishBasket"
			],
			"leveling": { "mutagenCost": 18 },
			"cloning": {
				"costBase": 425,
				"costLevel": 55,
				"timeBase": 2975,
				"timeLevel": 385
			},
			"falling": {
				"dmgMult": 80,
				"maxSpeed": 1550
			},
			"movementW": {
				"walk": { "base": 200, "sprint": 650 },
				"swim": { "base": 400 }
			},
			"movementD": {
				"walk": { "base": 200, "sprint": 650 },
				"swim": { "base": 400 }
			},
			"staminaRates": {
				"sprint": -6,
				"swimOrFly": -3
			},
			"attack": {
				"defaultDmg": 30,
				"defaultSwingRadius": 145,
				"attacks": [ { "name": "None", "interval": 0.4, "dmg": 15, "radius": 145, "stamina": 0 } ]
			},
			"death": {
				"lootBagChance": 1,
				"lootBags": [
					{
						"chance": 1,
						"item": "/Game/PrimalEarth/CoreBlueprints/Inventories/DinoDropInventoryComponent_Carnivore_Medium.DinoDropInventoryComponent_Carnivore_Medium"
					}
				],
				"baseXP": 8
			}
		},
		{
			"name": "Atlas Hydra",
			"bp": "/Game/Mods/AtlasPort/Critter/AtlasHydra/AHydra_character_BP.AHydra_character_BP_C",
			"dinoNameTag": "AtHydra",
			"customTag": "DragonRelic",
			"targetingTeamName": "Carnivores_High",
			"mass": 400,
			"dragWeight": 700,
			"flags": [
				"allowMountedWeaponry",
				"allowRiding",
				"canBeDragged",
				"canBeTorpid",
				"canDrag",
				"doStepDamage",
				"isAmphibious",
				"isBigDino",
				"isCarnivore",
				"isWaterDino",
				"isTameable"
			],
			"leveling": {
				"wildLevelTable": [ { "chance": 1, "min": 28, "max": 34 } ]
			},
			"falling": {
				"dmgMult": 80,
				"maxSpeed": 1550
			},
			"movementW": {
				"walk": { "base": 400, "sprint": 800 },
				"swim": { "base": 900, "sprint": 1800 }
			},
			"movementD": {
				"walk": { "base": 400, "sprint": 1600 },
				"swim": { "base": 900, "sprint": 3600 }
			},
			"staminaRates": {
				"sprint": -20,
				"swimOrFly": -3
			},
			"attack": {
				"defaultDmg": 45,
				"defaultSwingRadius": 300,
				"attacks": [
					{ "name": "BiteNomFury", "interval": 0.4, "dmg": 80, "radius": 400, "stamina": 0 },
					{ "name": "BiteNomFury", "interval": 0.4, "dmg": 90, "radius": 400, "stamina": 0 },
					{ "name": "BiteNomFury", "interval": 6, "dmg": 0, "radius": 400, "stamina": 300 },
					{ "name": "BiteNomFury", "interval": 20, "dmg": 100, "radius": 700, "stamina": 0 },
					{ "name": "BiteNomFury", "interval": 6, "dmg": 0, "radius": 400, "stamina": 300 }
				]
			},
			"death": {
				"lootBagChance": 1,
				"lootBags": [
					{
						"chance": 1,
						"item": "/Game/Mods/AtlasPort/Item/Mythos/DinoDropInventoryComponent_Mythos_Large.DinoDropInventoryComponent_Mythos_Large"
					}
				],
				"baseXP": 30
			}
		},
		{
			"name": "Flying Fisherman",
			"bp": "/Game/Mods/AtlasPort/Critter/Bat/ABat_Character_BP.ABat_Character_BP_C",
			"dinoNameTag": "Bat",
			"customTag": "ABat",
			"targetingTeamName": "Carnivores_Low",
			"mass": 165,
			"dragWeight": 85,
			"flags": [
				"allowFlyerLandedRider",
				"allowMountedWeaponry",
				"allowRiding",
				"canBeDragged",
				"canDrag",
				"isCarnivore",
				"isFlyerDino",
				"isTameable"
			],
			"leveling": { "mutagenCost": 24 },
			"cloning": {
				"costBase": 575,
				"costLevel": 55,
				"timeBase": 4025,
				"timeLevel": 385
			},
			"falling": {
				"dmgMult": 80,
				"maxSpeed": 1550
			},
			"movementW": {
				"walk": { "base": 0 },
				"fly": { "base": 800, "sprint": 1760 },
				"swim": { "base": 650 }
			},
			"movementD": {
				"walk": { "base": 0 },
				"fly": { "base": 800, "sprint": 1760 },
				"swim": { "base": 650 }
			},
			"staminaRates": { "swimOrFly": -3 },
			"attack": {
				"defaultDmg": 15,
				"defaultSwingRadius": 65,
				"attacks": [
					{ "name": "Melee", "interval": 0.5, "dmg": 26, "radius": 260, "stamina": 0 },
					{ "name": "Melee", "interval": 0.5, "dmg": 26, "radius": 260, "stamina": 0 },
					{ "name": "Melee", "interval": 0.5, "dmg": 0, "radius": 0, "stamina": 0 }
				]
			},
			"death": { "baseXP": 3 }
		},
		{
			"name": "Feral Boar",
			"bp": "/Game/Mods/AtlasPort/Critter/Boar/ABoar_Character_BP.ABoar_Character_BP_C",
			"dinoNameTag": "Daeodon",
			"customTag": "Boar",
			"targetingTeamName": "Herbivores_Medium_Aggressive",
			"mass": 165,
			"dragWeight": 112,
			"flags": [
				"allowMountedWeaponry",
				"allowRiding",
				"canBeDragged",
				"canBeTorpid",
				"canDrag",
				"isTameable"
			],
			"leveling": { "mutagenCost": 24 },
			"cloning": {
				"costBase": 575,
				"costLevel": 55,
				"timeBase": 4025,
				"timeLevel": 385
			},
			"falling": {
				"dmgMult": 80,
				"maxSpeed": 1550
			},
			"movementW": {
				"walk": { "base": 200, "sprint": 1200 },
				"swim": { "base": 300 }
			},
			"movementD": {
				"walk": { "base": 200, "sprint": 1200 },
				"swim": { "base": 300 }
			},
			"staminaRates": {
				"sprint": -7,
				"swimOrFly": -3
			},
			"attack": {
				"defaultDmg": 15,
				"defaultSwingRadius": 65,
				"attacks": [
					{ "name": "Melee", "interval": 0.2, "dmg": 20, "radius": 260, "stamina": 0 },
					{ "name": "Melee", "interval": 5, "dmg": 28, "radius": 260, "stamina": 0 },
					{ "name": "Melee", "interval": 0.2, "dmg": 0, "radius": 0, "stamina": 0 }
				]
			},
			"death": { "baseXP": 3 }
		},
		{
			"name": "Pampas Cat",
			"bp": "/Game/Mods/AtlasPort/Critter/Cat/PampasCat_Character_BP.PampasCat_Character_BP_C",
			"dinoNameTag": "Saber",
			"customTag": "Saber",
			"targetingTeamName": "Herbivores",
			"mass": 80,
			"dragWeight": 25,
			"flags": [
				"canBeDragged",
				"canBeTorpid",
				"canDrag",
				"canMountOnHumans",
				"isTameable"
			],
			"leveling": { "mutagenCost": 24 },
			"cloning": {
				"costBase": 575,
				"costLevel": 27.5,
				"timeBase": 4025,
				"timeLevel": 192.5
			},
			"falling": {
				"dmgMult": 0,
				"maxSpeed": 1550
			},
			"movementW": {
				"walk": { "base": 60, "sprint": 540 },
				"swim": { "base": 300 }
			},
			"movementD": {
				"walk": { "base": 60, "sprint": 540 },
				"swim": { "base": 300 }
			},
			"staminaRates": {
				"sprint": -4,
				"swimOrFly": -3
			},
			"attack": {
				"defaultDmg": 10,
				"defaultSwingRadius": 50,
				"attacks": [ { "name": "Melee", "interval": 0.4, "dmg": 15, "radius": 140, "stamina": 0 } ]
			},
			"death": { "baseXP": 2 }
		},
		{
			"name": "Pirareeba Catfish",
			"bp": "/Game/Mods/AtlasPort/Critter/Catfish/Catfish_Character_BP.Catfish_Character_BP_C",
			"dinoNameTag": "Salmon",
			"customTag": "",
			"targetingTeamName": "Carnivores_Low",
			"mass": 100,
			"dragWeight": 100,
			"flags": [
				"canBeDragged",
				"canDrag",
				"isWaterDino",
				"dieIfLeftWater",
				"isTameable",
				"canBeWildTrappedWithFishBasket",
				"canBeTamedWithFishBasket"
			],
			"falling": {
				"dmgMult": 80,
				"maxSpeed": 1550
			},
			"movementW": {
				"walk": { "base": 190, "sprint": 950 },
				"swim": { "base": 190 }
			},
			"movementD": {
				"walk": { "base": 190, "sprint": 950 },
				"swim": { "base": 190 }
			},
			"staminaRates": {
				"sprint": -19,
				"swimOrFly": -3
			},
			"attack": {
				"defaultDmg": 4,
				"defaultSwingRadius": 78,
				"attacks": [ { "name": "None", "interval": 0.5, "dmg": 25, "radius": 240, "stamina": 0 } ]
			},
			"death": { "baseXP": 0.5 }
		},
		{
			"name": "Derpmouth Cod",
			"bp": "/Game/Mods/AtlasPort/Critter/Cod/Cod_Character_BP.Cod_Character_BP_C",
			"dinoNameTag": "Salmon",
			"customTag": "",
			"targetingTeamName": "Herbivore_Water",
			"mass": 100,
			"dragWeight": 32.5,
			"flags": [
				"canBeDragged",
				"canDrag",
				"isWaterDino",
				"dieIfLeftWater",
				"isTameable",
				"canBeWildTrappedWithFishBasket",
				"canBeTamedWithFishBasket"
			],
			"falling": {
				"dmgMult": 80,
				"maxSpeed": 1550
			},
			"movementW": {
				"walk": { "base": 190, "sprint": 399 },
				"swim": { "base": 190 }
			},
			"movementD": {
				"walk": { "base": 190, "sprint": 399 },
				"swim": { "base": 190 }
			},
			"staminaRates": {
				"sprint": -4,
				"swimOrFly": -3
			},
			"attack": {
				"defaultDmg": 4,
				"defaultSwingRadius": 78,
				"attacks": [ { "name": "None", "interval": 1, "dmg": 4, "radius": 78, "stamina": 0 } ]
			},
			"death": { "baseXP": 0.5 }
		},
		{
			"name": "Bobbi",
			"bp": "/Game/Mods/AtlasPort/Critter/Cod/Cod_Character_BP_Bobbi.Cod_Character_BP_Bobbi_C",
			"dinoNameTag": "Salmon",
			"customTag": "",
			"targetingTeamName": "Herbivore_Water",
			"mass": 100,
			"dragWeight": 32.5,
			"flags": [
				"allowRiding",
				"canBeDragged",
				"canDrag",
				"isWaterDino",
				"dieIfLeftWater"
			],
			"leveling": {
				"wildLevelTable": [ { "chance": 1, "min": 28, "max": 50 } ]
			},
			"falling": {
				"dmgMult": 80,
				"maxSpeed": 1550
			},
			"movementW": {
				"walk": { "base": 190, "sprint": 1330 },
				"swim": { "base": 600 }
			},
			"movementD": {
				"walk": { "base": 190, "sprint": 1330 },
				"swim": { "base": 600 }
			},
			"staminaRates": {
				"sprint": -10,
				"swimOrFly": -3
			},
			"attack": {
				"defaultDmg": 4,
				"defaultSwingRadius": 78,
				"attacks": [ { "name": "None", "interval": 1, "dmg": 999, "radius": 700, "stamina": 0 } ]
			},
			"death": { "baseXP": 3000 }
		},
		{
			"name": "GlacierKing Crab ",
			"bp": "/Game/Mods/AtlasPort/Critter/Crab/ACrab_Character_BP.ACrab_Character_BP_C",
			"dinoNameTag": "CaveCrab",
			"customTag": "AtlasCrab",
			"targetingTeamName": "Carnivores_High",
			"mass": 400,
			"dragWeight": 450,
			"flags": [
				"allowMountedWeaponry",
				"allowRiding",
				"canBeDragged",
				"canBeTorpid",
				"canDrag",
				"isAmphibious",
				"isBigDino",
				"isCarnivore",
				"isTameable"
			],
			"leveling": { "mutagenCost": 51 },
			"cloning": {
				"costBase": 1250,
				"costLevel": 55,
				"timeBase": 8750,
				"timeLevel": 385
			},
			"falling": {
				"dmgMult": 20,
				"maxSpeed": 2800
			},
			"movementW": {
				"walk": { "base": 300, "sprint": 780 },
				"swim": { "base": 500, "sprint": 1300 }
			},
			"movementD": {
				"walk": { "base": 420, "sprint": 1092 },
				"swim": { "base": 700, "sprint": 1820 }
			},
			"staminaRates": {
				"sprint": -20,
				"swimOrFly": -3
			},
			"attack": {
				"defaultDmg": 20,
				"defaultSwingRadius": 110,
				"attacks": [
					{ "name": "ClawSpear", "interval": 0.1, "dmg": 32, "radius": 425, "stamina": 0 },
					{ "name": "ClawHammer", "interval": 2, "dmg": 60, "radius": 425, "stamina": 0 },
					{ "name": "ClawSpin", "interval": 6, "dmg": 55, "radius": 350, "stamina": 120 },
					{ "name": "ClawSpin", "interval": 2, "dmg": 0, "radius": 0, "stamina": 0 }
				]
			},
			"death": { "baseXP": 6 }
		},
		{
			"name": "Pelagic Crocodile",
			"bp": "/Game/Mods/AtlasPort/Critter/Crocodile/ACroc_Character_BP.ACroc_Character_BP_C",
			"dinoNameTag": "Sarco",
			"customTag": "Sarco",
			"targetingTeamName": "Carnivores_Medium",
			"mass": 220,
			"dragWeight": 250,
			"flags": [
				"allowCarryFlyerDinos",
				"allowMountedWeaponry",
				"allowRiding",
				"canBeDragged",
				"canBeTorpid",
				"canDrag",
				"isAmphibious",
				"isBigDino",
				"isCarnivore",
				"isWaterDino",
				"isTameable"
			],
			"leveling": { "mutagenCost": 23 },
			"cloning": {
				"costBase": 550,
				"costLevel": 55,
				"timeBase": 3850,
				"timeLevel": 385
			},
			"falling": {
				"dmgMult": 80,
				"maxSpeed": 1550
			},
			"movementW": {
				"walk": { "base": 150, "sprint": 825 },
				"swim": { "base": 750, "sprint": 1299.4 }
			},
			"movementD": {
				"walk": { "base": 165, "sprint": 907.5 },
				"swim": { "base": 825, "sprint": 1429.3 }
			},
			"staminaRates": {
				"sprint": -20,
				"swimOrFly": -3
			},
			"attack": {
				"defaultDmg": 35,
				"defaultSwingRadius": 160,
				"attacks": [
					{ "name": "Melee", "interval": 0.1, "dmg": 45, "radius": 240, "stamina": 0 },
					{ "name": "Roll", "interval": 10, "dmg": 55, "radius": 240, "stamina": 200 },
					{ "name": "Lunge", "interval": 5, "dmg": 55, "radius": 210, "stamina": 125 },
					{ "name": "MeleeLeft", "interval": 0.1, "dmg": 45, "radius": 240, "stamina": 0 },
					{ "name": "MeleeLeft", "interval": 0.1, "dmg": 45, "radius": 250, "stamina": 0 },
					{ "name": "Snarl", "interval": 0.1, "dmg": 0, "radius": 0, "stamina": 0 }
				]
			},
			"death": {
				"lootBagChance": 1,
				"lootBags": [
					{
						"chance": 1,
						"item": "/Game/PrimalEarth/CoreBlueprints/Inventories/DinoDropInventoryComponent_Carnivore_Large_Sarco.DinoDropInventoryComponent_Carnivore_Large_Sarco"
					}
				],
				"baseXP": 5
			}
		},
		{
			"name": "Arcane Pelagic Crocodile",
			"bp": "/Game/Mods/AtlasPort/Critter/Crocodile/ACroc_Character_BP_Arcane.ACroc_Character_BP_Arcane_C",
			"dinoNameTag": "Sarco",
			"customTag": "Sarco",
			"targetingTeamName": "Carnivores_Medium",
			"mass": 220,
			"dragWeight": 250,
			"flags": [
				"allowCarryFlyerDinos",
				"allowMountedWeaponry",
				"allowRiding",
				"canBeDragged",
				"canBeTorpid",
				"canDrag",
				"isAmphibious",
				"isBigDino",
				"isCarnivore",
				"isWaterDino",
				"isTameable"
			],
			"leveling": { "mutagenCost": 23 },
			"cloning": {
				"costBase": 550,
				"costLevel": 55,
				"timeBase": 3850,
				"timeLevel": 385
			},
			"falling": {
				"dmgMult": 80,
				"maxSpeed": 1550
			},
			"movementW": {
				"walk": { "base": 150, "sprint": 825 },
				"swim": { "base": 750, "sprint": 1299.4 }
			},
			"movementD": {
				"walk": { "base": 165, "sprint": 907.5 },
				"swim": { "base": 825, "sprint": 1429.3 }
			},
			"staminaRates": {
				"sprint": -20,
				"swimOrFly": -3
			},
			"attack": {
				"defaultDmg": 35,
				"defaultSwingRadius": 160,
				"attacks": [
					{ "name": "Melee", "interval": 0.1, "dmg": 45, "radius": 240, "stamina": 0 },
					{ "name": "Roll", "interval": 10, "dmg": 55, "radius": 240, "stamina": 200 },
					{ "name": "Lunge", "interval": 5, "dmg": 55, "radius": 210, "stamina": 125 },
					{ "name": "MeleeLeft", "interval": 0.1, "dmg": 45, "radius": 240, "stamina": 0 },
					{ "name": "MeleeLeft", "interval": 0.1, "dmg": 45, "radius": 250, "stamina": 0 },
					{ "name": "Snarl", "interval": 0.1, "dmg": 0, "radius": 0, "stamina": 0 }
				]
			},
			"death": {
				"lootBagChance": 1,
				"lootBags": [
					{
						"chance": 1,
						"item": "/Game/PrimalEarth/CoreBlueprints/Inventories/DinoDropInventoryComponent_Carnivore_Large_Sarco.DinoDropInventoryComponent_Carnivore_Large_Sarco"
					}
				],
				"baseXP": 5
			}
		},
		{
			"name": "Mongrel Cyclops",
			"bp": "/Game/Mods/AtlasPort/Critter/Cyclops/ACyclops_Character_bp.ACyclops_Character_bp_C",
			"dinoNameTag": "Monkey",
			"customTag": "",
			"targetingTeamName": "Carnivores_High",
			"mass": 400,
			"dragWeight": 550,
			"flags": [
				"allowMountedWeaponry",
				"allowRiding",
				"canBeDragged",
				"canBeTorpid",
				"canDrag",
				"doStepDamage",
				"isBigDino",
				"isCarnivore",
				"isTameable"
			],
			"leveling": {
				"wildLevelTable": [ { "chance": 1, "min": 21, "max": 30 } ]
			},
			"falling": {
				"dmgMult": 80,
				"maxSpeed": 1550
			},
			"movementW": {
				"walk": { "base": 450, "sprint": 1800 },
				"swim": { "base": 300 }
			},
			"movementD": {
				"walk": { "base": 450, "sprint": 1800 },
				"swim": { "base": 300 }
			},
			"staminaRates": {
				"sprint": -40,
				"swimOrFly": -3
			},
			"attack": {
				"defaultDmg": 45,
				"defaultSwingRadius": 300,
				"attacks": [
					{ "name": "Slaps", "interval": 0.4, "dmg": 85, "radius": 525, "stamina": 0 },
					{ "name": "Slam", "interval": 5, "dmg": 150, "radius": 525, "stamina": 100 },
					{ "name": "Uppercut", "interval": 10, "dmg": 100, "radius": 525, "stamina": 100 },
					{ "name": "Spin", "interval": 10, "dmg": 70, "radius": 525, "stamina": 100 },
					{ "name": "RawrMf", "interval": 5, "dmg": 0, "radius": 0, "stamina": 0 }
				]
			},
			"death": {
				"lootBagChance": 1,
				"lootBags": [
					{
						"chance": 1,
						"item": "/Game/Mods/AtlasPort/Item/Mythos/DinoDropInventoryComponent_Mythos_Large.DinoDropInventoryComponent_Mythos_Large"
					}
				],
				"baseXP": 30
			}
		},
		{
			"name": "Jiiba Dolphin",
			"bp": "/Game/Mods/AtlasPort/Critter/Dolphin/ADolphin_Character_BP.ADolphin_Character_BP_C",
			"dinoNameTag": "Dolphin",
			"customTag": "Dolphin",
			"targetingTeamName": "Carnivore_Water",
			"mass": 300,
			"dragWeight": 75,
			"flags": [
				"allowMountedWeaponry",
				"allowRiding",
				"canBeDragged",
				"canDrag",
				"isCarnivore",
				"isWaterDino",
				"dieIfLeftWater",
				"isTameable"
			],
			"leveling": { "mutagenCost": 66 },
			"cloning": {
				"costBase": 1650,
				"costLevel": 55,
				"timeBase": 11550,
				"timeLevel": 385
			},
			"falling": {
				"dmgMult": 80,
				"maxSpeed": 1550
			},
			"movementW": {
				"walk": { "base": 600, "sprint": 1200 },
				"swim": { "base": 1500 }
			},
			"movementD": {
				"walk": { "base": 600, "sprint": 1200 },
				"swim": { "base": 1500 }
			},
			"staminaRates": {
				"sprint": -10,
				"swimOrFly": -3
			},
			"attack": {
				"defaultDmg": 20,
				"defaultSwingRadius": 140,
				"attacks": [
					{ "name": "None", "interval": 0.55, "dmg": 15, "radius": 240, "stamina": 0 },
					{ "name": "Jump", "interval": 0.55, "dmg": 0, "radius": 0, "stamina": 0 }
				]
			},
			"death": { "baseXP": 4 }
		},
		{
			"name": "{TEMPLATE} Atlas Drake",
			"bp": "/Game/Mods/AtlasPort/Critter/Drake/ADrake_Character_BP.ADrake_Character_BP_C",
			"dinoNameTag": "Dragon",
			"customTag": "AtlasDrake",
			"targetingTeamName": "Carnivores_High",
			"mass": 800,
			"dragWeight": 550,
			"flags": [
				"allowFlyerLandedRider",
				"allowMountedWeaponry",
				"allowRiding",
				"canBeDragged",
				"canBeTorpid",
				"canDrag",
				"doStepDamage",
				"flyerAllowRidingInCaves",
				"isBigDino",
				"isCarnivore",
				"isFlyerDino",
				"isTameable"
			],
			"leveling": {
				"wildLevelTable": [
					{ "chance": 0.4, "min": 1, "max": 5 },
					{ "chance": 0.2, "min": 6, "max": 12 },
					{ "chance": 0.2, "min": 13, "max": 20 },
					{ "chance": 0.2, "min": 21, "max": 38 }
				]
			},
			"falling": {
				"dmgMult": 80,
				"maxSpeed": 1550
			},
			"movementW": {
				"walk": { "base": 300, "sprint": 1050 },
				"fly": { "base": 1500, "sprint": 4725 },
				"swim": { "base": 300 }
			},
			"movementD": {
				"walk": { "base": 300, "sprint": 1050 },
				"fly": { "base": 1500, "sprint": 4725 },
				"swim": { "base": 300 }
			},
			"staminaRates": {
				"sprint": -15,
				"swimOrFly": 0
			},
			"attack": {
				"defaultDmg": 45,
				"defaultSwingRadius": 300,
				"attacks": [
					{ "name": "Bite", "interval": 0.4, "dmg": 90, "radius": 600, "stamina": 0 },
					{ "name": "Projectile", "interval": 10, "dmg": 0, "radius": 0, "stamina": 100 },
					{ "name": "Claws", "interval": 8, "dmg": 62, "radius": 450, "stamina": 0 },
					{ "name": "Roar", "interval": 8, "dmg": 0, "radius": 0, "stamina": 0 },
					{ "name": "ExtraProjectile", "interval": 8, "dmg": 0, "radius": 0, "stamina": 0 }
				]
			},
			"death": {
				"lootBagChance": 1,
				"lootBags": [
					{
						"chance": 1,
						"item": "/Game/Mods/AtlasPort/Item/Mythos/DinoDropInventoryComponent_Mythos_Large.DinoDropInventoryComponent_Mythos_Large"
					}
				],
				"baseXP": 30
			}
		},
		{
			"name": "Atlas Flame Drake",
			"bp": "/Game/Mods/AtlasPort/Critter/Drake/ADrake_Character_BP_Fire.ADrake_Character_BP_Fire_C",
			"dinoNameTag": "AtFlameDrake",
			"customTag": "AtlasDrake",
			"targetingTeamName": "Carnivores_High",
			"mass": 800,
			"dragWeight": 550,
			"flags": [
				"allowFlyerLandedRider",
				"allowMountedWeaponry",
				"allowRiding",
				"canBeDragged",
				"canBeTorpid",
				"canDrag",
				"doStepDamage",
				"flyerAllowRidingInCaves",
				"isBigDino",
				"isCarnivore",
				"isFlyerDino",
				"isTameable"
			],
			"leveling": {
				"wildLevelTable": [
					{ "chance": 0.4, "min": 1, "max": 5 },
					{ "chance": 0.2, "min": 6, "max": 12 },
					{ "chance": 0.2, "min": 13, "max": 20 },
					{ "chance": 0.2, "min": 21, "max": 38 }
				]
			},
			"falling": {
				"dmgMult": 80,
				"maxSpeed": 1550
			},
			"movementW": {
				"walk": { "base": 300, "sprint": 1050 },
				"fly": { "base": 1500, "sprint": 4725 },
				"swim": { "base": 300 }
			},
			"movementD": {
				"walk": { "base": 300, "sprint": 1050 },
				"fly": { "base": 1500, "sprint": 4725 },
				"swim": { "base": 300 }
			},
			"staminaRates": {
				"sprint": -15,
				"swimOrFly": 0
			},
			"attack": {
				"defaultDmg": 45,
				"defaultSwingRadius": 300,
				"attacks": [
					{ "name": "Bite", "interval": 0.4, "dmg": 90, "radius": 600, "stamina": 0 },
					{ "name": "Projectile", "interval": 10, "dmg": 0, "radius": 0, "stamina": 100 },
					{ "name": "Claws", "interval": 8, "dmg": 62, "radius": 450, "stamina": 0 },
					{ "name": "Roar", "interval": 8, "dmg": 0, "radius": 0, "stamina": 0 },
					{ "name": "ExtraProjectile", "interval": 10, "dmg": 0, "radius": 0, "stamina": 200 }
				]
			},
			"death": {
				"lootBagChance": 1,
				"lootBags": [
					{
						"chance": 1,
						"item": "/Game/Mods/AtlasPort/Item/Mythos/DinoDropInventoryComponent_Mythos_Large.DinoDropInventoryComponent_Mythos_Large"
					}
				],
				"baseXP": 30
			}
		},
		{
			"name": "Atlas Storm Drake",
			"bp": "/Game/Mods/AtlasPort/Critter/Drake/ADrake_Character_BP_Storm.ADrake_Character_BP_Storm_C",
			"dinoNameTag": "Dragon",
			"customTag": "AtlasDrake",
			"targetingTeamName": "Carnivores_High",
			"mass": 800,
			"dragWeight": 550,
			"flags": [
				"allowFlyerLandedRider",
				"allowMountedWeaponry",
				"allowRiding",
				"canBeDragged",
				"canBeTorpid",
				"canDrag",
				"doStepDamage",
				"flyerAllowRidingInCaves",
				"isBigDino",
				"isCarnivore",
				"isFlyerDino",
				"isTameable"
			],
			"leveling": {
				"wildLevelTable": [
					{ "chance": 0.4, "min": 1, "max": 5 },
					{ "chance": 0.2, "min": 6, "max": 12 },
					{ "chance": 0.2, "min": 13, "max": 20 },
					{ "chance": 0.2, "min": 21, "max": 38 }
				]
			},
			"falling": {
				"dmgMult": 80,
				"maxSpeed": 1550
			},
			"movementW": {
				"walk": { "base": 300, "sprint": 1050 },
				"fly": { "base": 1500, "sprint": 4725 },
				"swim": { "base": 300 }
			},
			"movementD": {
				"walk": { "base": 300, "sprint": 1050 },
				"fly": { "base": 1500, "sprint": 4725 },
				"swim": { "base": 300 }
			},
			"staminaRates": {
				"sprint": -15,
				"swimOrFly": 0
			},
			"attack": {
				"defaultDmg": 45,
				"defaultSwingRadius": 300,
				"attacks": [
					{ "name": "Bite", "interval": 0.4, "dmg": 90, "radius": 600, "stamina": 0 },
					{ "name": "Projectile", "interval": 15, "dmg": 0, "radius": 0, "stamina": 300 },
					{ "name": "Claws", "interval": 8, "dmg": 62, "radius": 450, "stamina": 0 },
					{ "name": "Roar", "interval": 8, "dmg": 0, "radius": 0, "stamina": 0 },
					{ "name": "WindBreath", "interval": 10, "dmg": 0, "radius": 0, "stamina": 180 }
				]
			},
			"death": {
				"lootBagChance": 1,
				"lootBags": [
					{
						"chance": 1,
						"item": "/Game/Mods/AtlasPort/Item/Mythos/DinoDropInventoryComponent_Mythos_Large.DinoDropInventoryComponent_Mythos_Large"
					}
				],
				"baseXP": 30
			}
		},
		{
			"name": "Midgard Moray",
			"bp": "/Game/Mods/AtlasPort/Critter/Eel/AEel_Character_bp.AEel_Character_bp_C",
			"dinoNameTag": "Eel",
			"customTag": "MidgardEel",
			"targetingTeamName": "Carnivore_Water_PlayerOrTamed",
			"mass": 300,
			"dragWeight": 250,
			"flags": [
				"allowRiding",
				"canBeDragged",
				"canBeTorpid",
				"canDrag",
				"isCarnivore",
				"isWaterDino",
				"dieIfLeftWater",
				"isTameable",
				"canBeWildTrappedWithFishBasket",
				"canBeTamedWithFishBasket"
			],
			"leveling": { "mutagenCost": 38 },
			"cloning": {
				"costBase": 925,
				"costLevel": 55,
				"timeBase": 6475,
				"timeLevel": 385
			},
			"falling": {
				"dmgMult": 80,
				"maxSpeed": 1550
			},
			"movementW": {
				"walk": { "base": 1000, "sprint": 3500 }
			},
			"movementD": {
				"walk": { "base": 1000, "sprint": 3500 }
			},
			"staminaRates": { "sprint": -5 },
			"attack": {
				"defaultDmg": 40,
				"defaultSwingRadius": 170,
				"attacks": [ { "name": "None", "interval": 0.2, "dmg": 55, "radius": 340, "stamina": 0 } ]
			},
			"death": { "baseXP": 12 }
		},
		{
			"name": "Forest Elephant",
			"bp": "/Game/Mods/AtlasPort/Critter/Elephant/AElephant_Character_BP.AElephant_Character_BP_C",
			"dinoNameTag": "Mammoth",
			"customTag": "Mammoth",
			"targetingTeamName": "Herbivores_Large",
			"mass": 340,
			"dragWeight": 550,
			"flags": [
				"allowRiding",
				"canBeDragged",
				"canBeTorpid",
				"canDrag",
				"doStepDamage",
				"isBigDino",
				"isTameable"
			],
			"leveling": { "mutagenCost": 62 },
			"cloning": {
				"costBase": 1550,
				"costLevel": 55,
				"timeBase": 10850,
				"timeLevel": 385
			},
			"falling": {
				"dmgMult": 80,
				"maxSpeed": 1550
			},
			"movementW": {
				"walk": { "base": 150, "sprint": 1200 },
				"swim": { "base": 480 }
			},
			"movementD": {
				"walk": { "base": 150, "sprint": 1200 },
				"swim": { "base": 480 }
			},
			"staminaRates": {
				"sprint": -14,
				"swimOrFly": -3
			},
			"attack": {
				"defaultDmg": 42,
				"defaultSwingRadius": 500,
				"attacks": [
					{ "name": "Tusk Attacks", "interval": 0.5, "dmg": 55, "radius": 500, "stamina": 20 },
					{ "name": "Stomp", "interval": 3, "dmg": 72, "radius": 800, "stamina": 20 },
					{ "name": "Taunt", "interval": 0.5, "dmg": 0, "radius": 500, "stamina": 20 }
				]
			},
			"death": { "baseXP": 8 }
		},
		{
			"name": "Aberrant Forest Elephant",
			"bp": "/Game/Mods/AtlasPort/Critter/Elephant/AElephant_Character_BP_Aberrant.AElephant_Character_BP_Aberrant_C",
			"dinoNameTag": "Mammoth",
			"customTag": "Mammoth",
			"targetingTeamName": "Herbivores_Large",
			"mass": 340,
			"dragWeight": 550,
			"flags": [
				"allowRiding",
				"canBeDragged",
				"canBeTorpid",
				"canDrag",
				"doStepDamage",
				"isBigDino",
				"isTameable"
			],
			"leveling": { "mutagenCost": 62 },
			"cloning": {
				"costBase": 1550,
				"costLevel": 55,
				"timeBase": 10850,
				"timeLevel": 385
			},
			"falling": {
				"dmgMult": 80,
				"maxSpeed": 1550
			},
			"movementW": {
				"walk": { "base": 150, "sprint": 1200 },
				"swim": { "base": 480 }
			},
			"movementD": {
				"walk": { "base": 150, "sprint": 1200 },
				"swim": { "base": 480 }
			},
			"staminaRates": {
				"sprint": -14,
				"swimOrFly": -3
			},
			"attack": {
				"defaultDmg": 42,
				"defaultSwingRadius": 500,
				"attacks": [
					{ "name": "Tusk Attacks", "interval": 0.5, "dmg": 55, "radius": 500, "stamina": 20 },
					{ "name": "Stomp", "interval": 3, "dmg": 72, "radius": 800, "stamina": 20 },
					{ "name": "Taunt", "interval": 0.5, "dmg": 0, "radius": 500, "stamina": 20 }
				]
			},
			"death": { "baseXP": 8 }
		},
		{
			"name": "Atlas Giraffe",
			"bp": "/Game/Mods/AtlasPort/Critter/Giraffe/AGiraffe_Character_BP.AGiraffe_Character_BP_C",
			"dinoNameTag": "Paracer",
			"customTag": "Giraffe",
			"targetingTeamName": "Herbivores_Large",
			"mass": 360,
			"dragWeight": 600,
			"flags": [
				"allowRiding",
				"canBeDragged",
				"canBeTorpid",
				"canDrag",
				"doStepDamage",
				"isBigDino",
				"isTameable"
			],
			"leveling": { "mutagenCost": 66 },
			"cloning": {
				"costBase": 1650,
				"costLevel": 55,
				"timeBase": 11550,
				"timeLevel": 385
			},
			"falling": {
				"dmgMult": 80,
				"maxSpeed": 1550
			},
			"movementW": {
				"walk": { "base": 350, "sprint": 1400 },
				"swim": { "base": 300 }
			},
			"movementD": {
				"walk": { "base": 350, "sprint": 1400 },
				"swim": { "base": 300 }
			},
			"staminaRates": {
				"sprint": -14,
				"swimOrFly": -3
			},
			"attack": {
				"defaultDmg": 45,
				"defaultSwingRadius": 550,
				"attacks": [
					{ "name": "Footstomp", "interval": 0.375, "dmg": 35, "radius": 550, "stamina": 0 },
					{ "name": "HeadSwing", "interval": 4, "dmg": 45, "radius": 550, "stamina": 0 }
				]
			},
			"death": { "baseXP": 12 }
		},
		{
			"name": "Aberrant Atlas Giraffe",
			"bp": "/Game/Mods/AtlasPort/Critter/Giraffe/AGiraffe_Character_BP_Aberrant.AGiraffe_Character_BP_Aberrant_C",
			"dinoNameTag": "Paracer",
			"customTag": "Giraffe",
			"targetingTeamName": "Herbivores_Large",
			"mass": 360,
			"dragWeight": 600,
			"flags": [
				"allowRiding",
				"canBeDragged",
				"canBeTorpid",
				"canDrag",
				"doStepDamage",
				"isBigDino",
				"isTameable"
			],
			"leveling": { "mutagenCost": 66 },
			"cloning": {
				"costBase": 1650,
				"costLevel": 55,
				"timeBase": 11550,
				"timeLevel": 385
			},
			"falling": {
				"dmgMult": 80,
				"maxSpeed": 1550
			},
			"movementW": {
				"walk": { "base": 350, "sprint": 1400 },
				"swim": { "base": 300 }
			},
			"movementD": {
				"walk": { "base": 350, "sprint": 1400 },
				"swim": { "base": 300 }
			},
			"staminaRates": {
				"sprint": -14,
				"swimOrFly": -3
			},
			"attack": {
				"defaultDmg": 45,
				"defaultSwingRadius": 550,
				"attacks": [
					{ "name": "Footstomp", "interval": 0.375, "dmg": 35, "radius": 550, "stamina": 0 },
					{ "name": "HeadSwing", "interval": 4, "dmg": 45, "radius": 550, "stamina": 0 }
				]
			},
			"death": { "baseXP": 12 }
		},
		{
			"name": "Aegis",
			"bp": "/Game/Mods/AtlasPort/Critter/GoodWhale/Aegis_Character_BP.Aegis_Character_BP_C",
			"dinoNameTag": "Basilosaurus",
			"customTag": "Aegis",
			"targetingTeamName": "Carnivore_Water",
			"mass": 800,
			"dragWeight": 450,
			"flags": [
				"allowRiding",
				"canBeDragged",
				"canBeTorpid",
				"canDrag",
				"isBigDino",
				"isWaterDino",
				"dieIfLeftWater",
				"isTameable"
			],
			"falling": {
				"dmgMult": 0,
				"maxSpeed": 1550
			},
			"movementW": {
				"walk": { "base": 300, "sprint": 1050 },
				"swim": { "base": 440 }
			},
			"movementD": {
				"walk": { "base": 360, "sprint": 1260 },
				"swim": { "base": 528 }
			},
			"staminaRates": {
				"sprint": 0,
				"swimOrFly": -3
			},
			"attack": {
				"defaultDmg": 100,
				"defaultSwingRadius": 650,
				"attacks": [ { "name": "Bite", "interval": 0.5, "dmg": 34, "radius": 500, "stamina": 0 } ]
			},
			"death": { "baseXP": 4 }
		},
		{
			"name": "Gorgon",
			"bp": "/Game/Mods/AtlasPort/Critter/Gorgon/AGorgon_Character_bp.AGorgon_Character_bp_C",
			"dinoNameTag": "Titanboa",
			"customTag": "Naga",
			"targetingTeamName": "Carnivores_Medium",
			"mass": 400,
			"dragWeight": 550,
			"flags": [
				"allowMountedWeaponry",
				"canBeDragged",
				"canBeTorpid",
				"canDrag",
				"isBigDino",
				"isCarnivore",
				"isTameable"
			],
			"falling": {
				"dmgMult": 80,
				"maxSpeed": 1550
			},
			"movementW": {
				"walk": { "base": 300, "sprint": 1350 },
				"swim": { "base": 900 }
			},
			"movementD": {
				"walk": { "base": 300, "sprint": 1350 },
				"swim": { "base": 900 }
			},
			"staminaRates": {
				"sprint": -40,
				"swimOrFly": -3
			},
			"attack": {
				"defaultDmg": 45,
				"defaultSwingRadius": 300,
				"attacks": [
					{ "name": "Claws", "interval": 0.4, "dmg": 45, "radius": 200, "stamina": 0 },
					{ "name": "Scream", "interval": 30, "dmg": 50, "radius": 600, "stamina": 0 },
					{ "name": "Proj", "interval": 10, "dmg": 0, "radius": 0, "stamina": 100 },
					{ "name": "Noodles", "interval": 180, "dmg": 0, "radius": 0, "stamina": 200 }
				]
			},
			"death": {
				"lootBagChance": 1,
				"lootBags": [
					{
						"chance": 1,
						"item": "/Game/Mods/AtlasPort/Item/Mythos/DinoDropInventoryComponent_Mythos_Small.DinoDropInventoryComponent_Mythos_Small"
					}
				],
				"baseXP": 30
			}
		},
		{
			"name": "Apophis Rattlesnake",
			"bp": "/Game/Mods/AtlasPort/Critter/Gorgon/ARattler_Character_bp_Minion.ARattler_Character_bp_Minion_C",
			"dinoNameTag": "Titanboa",
			"customTag": "Naga",
			"targetingTeamName": "Carnivores_Medium",
			"mass": 400,
			"dragWeight": 300,
			"variants": [ "Minion" ],
			"flags": [
				"allowMountedWeaponry",
				"allowRiding",
				"canBeDragged",
				"canBeTorpid",
				"canDrag",
				"isAmphibious",
				"isBigDino",
				"isCarnivore"
			],
			"falling": {
				"dmgMult": 80,
				"maxSpeed": 1550
			},
			"movementW": {
				"walk": { "base": 300, "sprint": 1650 },
				"swim": { "base": 700 }
			},
			"movementD": {
				"walk": { "base": 300, "sprint": 1650 },
				"swim": { "base": 700 }
			},
			"staminaRates": {
				"sprint": -40,
				"swimOrFly": -3
			},
			"attack": {
				"defaultDmg": 45,
				"defaultSwingRadius": 300,
				"attacks": [
					{ "name": "BiteNomFury", "interval": 0.4, "dmg": 40, "radius": 400, "stamina": 0 },
					{ "name": "BiteNomFury", "interval": 0.4, "dmg": 0, "radius": 0, "stamina": 25 },
					{ "name": "BiteNomFury", "interval": 0.4, "dmg": 0, "radius": 0, "stamina": 0 }
				]
			},
			"death": { "baseXP": 30 }
		},
		{
			"name": "Naga",
			"bp": "/Game/Mods/AtlasPort/Critter/Gorgon/Naga_Character_bp_Minion.Naga_Character_bp_Minion_C",
			"dinoNameTag": "Titanboa",
			"customTag": "Naga",
			"targetingTeamName": "Carnivores_Medium",
			"mass": 400,
			"dragWeight": 300,
			"variants": [ "Minion" ],
			"flags": [
				"allowMountedWeaponry",
				"allowRiding",
				"canBeDragged",
				"canBeTorpid",
				"canDrag",
				"isAmphibious",
				"isBigDino",
				"isCarnivore"
			],
			"falling": {
				"dmgMult": 80,
				"maxSpeed": 1550
			},
			"movementW": {
				"walk": { "base": 300, "sprint": 1800 },
				"swim": { "base": 900, "sprint": 5400 }
			},
			"movementD": {
				"walk": { "base": 300, "sprint": 1800 },
				"swim": { "base": 900, "sprint": 5400 }
			},
			"staminaRates": {
				"sprint": -40,
				"swimOrFly": -3
			},
			"attack": {
				"defaultDmg": 45,
				"defaultSwingRadius": 300,
				"attacks": [
					{ "name": "Bite", "interval": 0.4, "dmg": 30, "radius": 400, "stamina": 0 },
					{ "name": "Spittle", "interval": 10, "dmg": 0, "radius": 240, "stamina": 180 },
					{ "name": "Tails", "interval": 10, "dmg": 20, "radius": 450, "stamina": 50 },
					{ "name": "Rawr", "interval": 10, "dmg": 0, "radius": 0, "stamina": 0 }
				]
			},
			"death": { "baseXP": 30 }
		},
		{
			"name": "Savage Hammerhead",
			"bp": "/Game/Mods/AtlasPort/Critter/Hammerhead/AHammerhead_Character_bp.AHammerhead_Character_bp_C",
			"dinoNameTag": "Mega",
			"customTag": "AHammer",
			"targetingTeamName": "Carnivore_Water",
			"mass": 300,
			"dragWeight": 300,
			"flags": [
				"allowCarryFlyerDinos",
				"allowRiding",
				"canBeDragged",
				"canBeTorpid",
				"canDrag",
				"isCarnivore",
				"isWaterDino",
				"dieIfLeftWater",
				"isTameable"
			],
			"leveling": { "mutagenCost": 38 },
			"cloning": {
				"costBase": 925,
				"costLevel": 55,
				"timeBase": 6475,
				"timeLevel": 385
			},
			"falling": {
				"dmgMult": 80,
				"maxSpeed": 1550
			},
			"movementW": {
				"walk": { "base": 230, "sprint": 1380 },
				"swim": { "base": 230 }
			},
			"movementD": {
				"walk": { "base": 517.5, "sprint": 3105 },
				"swim": { "base": 517.5 }
			},
			"staminaRates": {
				"sprint": -10,
				"swimOrFly": -3
			},
			"attack": {
				"defaultDmg": 40,
				"defaultSwingRadius": 170,
				"attacks": [
					{ "name": "None", "interval": 0.2, "dmg": 42, "radius": 300, "stamina": 0 },
					{ "name": "None", "interval": 10, "dmg": 42, "radius": 300, "stamina": 0 }
				]
			},
			"death": { "baseXP": 12 }
		},
		{
			"name": "Atlas Horse",
			"bp": "/Game/Mods/AtlasPort/Critter/Horse/AHorse_Character_BP.AHorse_Character_BP_C",
			"dinoNameTag": "Equus",
			"customTag": "Equus",
			"targetingTeamName": "Herbivores_Medium_Aggressive",
			"mass": 175,
			"dragWeight": 125,
			"flags": [
				"allowMountedWeaponry",
				"allowRiding",
				"canBeDragged",
				"canBeTorpid",
				"canDrag",
				"isTameable"
			],
			"leveling": { "mutagenCost": 45 },
			"cloning": {
				"costBase": 1100,
				"costLevel": 55,
				"timeBase": 7700,
				"timeLevel": 385
			},
			"falling": {
				"dmgMult": 80,
				"maxSpeed": 1550
			},
			"movementW": {
				"walk": { "base": 292.5, "sprint": 1901.2 },
				"swim": { "base": 390 }
			},
			"movementD": {
				"walk": { "base": 292.5, "sprint": 1901.2 },
				"swim": { "base": 390 }
			},
			"staminaRates": {
				"sprint": -2.5,
				"swimOrFly": -3
			},
			"attack": {
				"defaultDmg": 8,
				"defaultSwingRadius": 170,
				"attacks": [
					{ "name": "Melee", "interval": 0.4, "dmg": 15, "radius": 220, "stamina": 0 },
					{ "name": "BuckKick", "interval": 0.4, "dmg": 28, "radius": 220, "stamina": 80 },
					{ "name": "Whinney", "interval": 0.4, "dmg": 0, "radius": 300, "stamina": 0 },
					{ "name": "BuckFeedResponse", "interval": 0.4, "dmg": 0, "radius": 300, "stamina": 0 }
				]
			},
			"death": { "baseXP": 1 }
		},
		{
			"name": "Atlas Kodiak",
			"bp": "/Game/Mods/AtlasPort/Critter/Kodiak/AKodiak_Character_bp.AKodiak_Character_bp_C",
			"dinoNameTag": "Direbear",
			"customTag": "Direbear",
			"targetingTeamName": "Carnivores_High",
			"mass": 400,
			"dragWeight": 550,
			"flags": [
				"allowMountedWeaponry",
				"allowRiding",
				"canBeDragged",
				"canBeTorpid",
				"canDrag",
				"isBigDino",
				"isCarnivore",
				"isTameable"
			],
			"falling": {
				"dmgMult": 80,
				"maxSpeed": 1550
			},
			"movementW": {
				"walk": { "base": 270, "sprint": 1620 },
				"swim": { "base": 700 }
			},
			"movementD": {
				"walk": { "base": 270, "sprint": 1620 },
				"swim": { "base": 700 }
			},
			"movementR": {
				"walk": { "base": 270, "sprint": 3693.6 },
				"swim": { "base": 700 }
			},
			"staminaRates": {
				"sprint": -14,
				"swimOrFly": -3
			},
			"attack": {
				"defaultDmg": 45,
				"defaultSwingRadius": 300,
				"attacks": [
					{ "name": "Bite", "interval": 0.4, "dmg": 54, "radius": 300, "stamina": 0 },
					{ "name": "Clawslap", "interval": 2, "dmg": 70, "radius": 300, "stamina": 0 },
					{ "name": "Roar", "interval": 0.4, "dmg": 0, "radius": 240, "stamina": 0 },
					{ "name": "Claws", "interval": 0.4, "dmg": 58, "radius": 300, "stamina": 75 },
					{ "name": "BEARBOMB", "interval": 0.4, "dmg": 80, "radius": 300, "stamina": 0 }
				]
			},
			"death": { "baseXP": 30 }
		},
		{
			"name": "Leatherwing",
			"bp": "/Game/Mods/AtlasPort/Critter/Leatherwing/Leatherwing_character_bp.Leatherwing_character_bp_C",
			"dinoNameTag": "Ptera",
			"customTag": "Ptera",
			"targetingTeamName": "Carnivores_Medium",
			"mass": 190,
			"dragWeight": 150,
			"flags": [
				"allowFlyerLandedRider",
				"allowRiding",
				"canBeDragged",
				"canBeTorpid",
				"canDrag",
				"isFlyerDino",
				"preventCharacterBasing",
				"isTameable"
			],
			"leveling": { "mutagenCost": 79 },
			"cloning": {
				"costBase": 1975,
				"costLevel": 55,
				"timeBase": 13825,
				"timeLevel": 385
			},
			"falling": {
				"dmgMult": 80,
				"maxSpeed": 1550
			},
			"movementW": {
				"walk": { "base": 180, "sprint": 496.8 },
				"fly": { "base": 900, "sprint": 2484 },
				"swim": { "base": 300 }
			},
			"movementD": {
				"walk": { "base": 180, "sprint": 496.8 },
				"fly": { "base": 900, "sprint": 2484 },
				"swim": { "base": 300 }
			},
			"staminaRates": {
				"sprint": -10,
				"swimOrFly": -3
			},
			"attack": {
				"defaultDmg": 15,
				"defaultSwingRadius": 200,
				"attacks": [
					{ "name": "Bite", "interval": 0.6, "dmg": 25, "radius": 200, "stamina": 0 },
					{ "name": "GrabNab", "interval": 1, "dmg": 30, "radius": 200, "stamina": 5 },
					{ "name": "Drill Run", "interval": 15, "dmg": 35, "radius": 260, "stamina": 60 },
					{ "name": "Drill Run", "interval": 0.6, "dmg": 0, "radius": 0, "stamina": 0 }
				]
			},
			"death": { "baseXP": 3 }
		},
		{
			"name": "Leech Viper",
			"bp": "/Game/Mods/AtlasPort/Critter/LeechViper/LeechViper_Character_bp.LeechViper_Character_bp_C",
			"dinoNameTag": "Titanboa",
			"customTag": "",
			"targetingTeamName": "Carnivore_Water_PlayerOrTamed",
			"mass": 300,
			"dragWeight": 25,
			"flags": [
				"canBeDragged",
				"canDrag",
				"isWaterDino",
				"dieIfLeftWater",
				"isTameable",
				"canBeWildTrappedWithFishBasket",
				"canBeTamedWithFishBasket"
			],
			"leveling": { "mutagenCost": 38 },
			"cloning": {
				"costBase": 925,
				"costLevel": 55,
				"timeBase": 6475,
				"timeLevel": 385
			},
			"falling": {
				"dmgMult": 80,
				"maxSpeed": 1550
			},
			"movementW": {
				"walk": { "base": 300, "sprint": 1200 },
				"swim": { "base": 100 }
			},
			"movementD": {
				"walk": { "base": 675, "sprint": 2700 },
				"swim": { "base": 225 }
			},
			"staminaRates": {
				"sprint": -4,
				"swimOrFly": -3
			},
			"attack": {
				"defaultDmg": 40,
				"defaultSwingRadius": 170,
				"attacks": [
					{ "name": "None", "interval": 0.2, "dmg": 10, "radius": 220, "stamina": 0 },
					{ "name": "None", "interval": 5, "dmg": 10, "radius": 220, "stamina": 0 }
				]
			},
			"death": { "baseXP": 12 }
		},
		{
			"name": "Lion",
			"bp": "/Game/Mods/AtlasPort/Critter/Lion/Lion_Character_BP.Lion_Character_BP_C",
			"dinoNameTag": "Sabertooth",
			"customTag": "Lion",
			"targetingTeamName": "Carnivores_Medium",
			"mass": 195,
			"dragWeight": 120,
			"flags": [
				"allowMountedWeaponry",
				"allowRiding",
				"canBeDragged",
				"canBeTorpid",
				"canDrag",
				"isCarnivore",
				"isTameable"
			],
			"leveling": { "mutagenCost": 58 },
			"cloning": {
				"costBase": 1450,
				"costLevel": 55,
				"timeBase": 10150,
				"timeLevel": 385
			},
			"falling": {
				"dmgMult": 80,
				"maxSpeed": 1550
			},
			"movementW": {
				"walk": { "base": 279, "sprint": 1674 },
				"swim": { "base": 300 }
			},
			"movementD": {
				"walk": { "base": 279, "sprint": 1674 },
				"swim": { "base": 300 }
			},
			"staminaRates": {
				"sprint": -7,
				"swimOrFly": -3
			},
			"attack": {
				"defaultDmg": 33,
				"defaultSwingRadius": 160,
				"attacks": [
					{ "name": "None", "interval": 0.2, "dmg": 35, "radius": 240, "stamina": 0 },
					{ "name": "None", "interval": 0.2, "dmg": 0, "radius": 0, "stamina": 0 }
				]
			},
			"death": {
				"lootBagChance": 0.3,
				"lootBags": [
					{
						"chance": 1,
						"item": "/Game/PrimalEarth/CoreBlueprints/Inventories/DinoDropInventoryComponent_Carnivore_Medium.DinoDropInventoryComponent_Carnivore_Medium"
					}
				],
				"baseXP": 6
			}
		},
		{
			"name": "Phantom Manta",
			"bp": "/Game/Mods/AtlasPort/Critter/Manta/AManta_Character_BP.AManta_Character_BP_C",
			"dinoNameTag": "Manta",
			"customTag": "Manta",
			"targetingTeamName": "Herbivore_Water",
			"mass": 300,
			"dragWeight": 280,
			"flags": [
				"allowRiding",
				"canBeDragged",
				"canBeTorpid",
				"canDrag",
				"isCarnivore",
				"isWaterDino",
				"dieIfLeftWater",
				"isTameable"
			],
			"leveling": { "mutagenCost": 38 },
			"cloning": {
				"costBase": 925,
				"costLevel": 55,
				"timeBase": 6475,
				"timeLevel": 385
			},
			"falling": {
				"dmgMult": 80,
				"maxSpeed": 1550
			},
			"movementW": {
				"walk": { "base": 1000, "sprint": 2000 },
				"swim": { "base": 1000 }
			},
			"movementD": {
				"walk": { "base": 1000, "sprint": 2000 },
				"swim": { "base": 1000 }
			},
			"staminaRates": {
				"sprint": -20,
				"swimOrFly": -3
			},
			"attack": {
				"defaultDmg": 40,
				"defaultSwingRadius": 170,
				"attacks": [
					{ "name": "None", "interval": 0.2, "dmg": 25, "radius": 240, "stamina": 0 },
					{ "name": "None", "interval": 0.2, "dmg": 5, "radius": 240, "stamina": 0 }
				]
			},
			"death": { "baseXP": 12 }
		},
		{
			"name": "Nyoomarlin",
			"bp": "/Game/Mods/AtlasPort/Critter/Marlin/Marlin_Character_BP.Marlin_Character_BP_C",
			"dinoNameTag": "Salmon",
			"customTag": "",
			"targetingTeamName": "Herbivore_Water",
			"mass": 100,
			"dragWeight": 32.5,
			"flags": [
				"canBeDragged",
				"canDrag",
				"isWaterDino",
				"dieIfLeftWater",
				"isTameable",
				"canBeWildTrappedWithFishBasket",
				"canBeTamedWithFishBasket"
			],
			"falling": {
				"dmgMult": 80,
				"maxSpeed": 1550
			},
			"movementW": {
				"walk": { "base": 190, "sprint": 1710 },
				"swim": { "base": 190 }
			},
			"movementD": {
				"walk": { "base": 190, "sprint": 1710 },
				"swim": { "base": 190 }
			},
			"staminaRates": {
				"sprint": -4,
				"swimOrFly": -3
			},
			"attack": {
				"defaultDmg": 4,
				"defaultSwingRadius": 78,
				"attacks": [ { "name": "None", "interval": 1, "dmg": 10, "radius": 78, "stamina": 0 } ]
			},
			"death": { "baseXP": 0.5 }
		},
		{
			"name": "Leviathan, Lord of the Seas",
			"bp": "/Game/Mods/AtlasPort/Critter/MeanWhale/LeviathanSAA_character_Bp.LeviathanSAA_character_Bp_C",
			"dinoNameTag": "Basilosaurus",
			"customTag": "Harbinger",
			"targetingTeamName": "Carnivores_Low",
			"mass": 300,
			"dragWeight": 899,
			"variants": [ "Boss" ],
			"flags": [
				"allowCarryFlyerDinos",
				"allowRiding",
				"canBeDragged",
				"canDrag",
				"isBossDino",
				"isCarnivore",
				"isWaterDino",
				"dieIfLeftWater"
			],
			"cloning": {
				"costBase": 925,
				"costLevel": 55,
				"timeBase": 6475,
				"timeLevel": 385
			},
			"falling": {
				"dmgMult": 80,
				"maxSpeed": 1550
			},
			"movementW": {
				"walk": { "base": 400, "sprint": 1200 },
				"swim": { "base": 800 }
			},
			"movementD": {
				"walk": { "base": 900, "sprint": 2700 },
				"swim": { "base": 1800 }
			},
			"staminaRates": {
				"sprint": -20,
				"swimOrFly": -3
			},
			"attack": {
				"defaultDmg": 90,
				"defaultSwingRadius": 190,
				"attacks": [
					{ "name": "Bite", "interval": 0.4, "dmg": 750, "radius": 1800, "stamina": 0 },
					{ "name": "SavageBite", "interval": 8, "dmg": 900, "radius": 1800, "stamina": 0 },
					{ "name": "Roar", "interval": 10, "dmg": 0, "radius": 0, "stamina": 0 }
				]
			},
			"death": { "baseXP": 40 }
		},
		{
			"name": "Harbinger",
			"bp": "/Game/Mods/AtlasPort/Critter/MeanWhale/harbinger_character_Bp.Harbinger_Character_BP_C",
			"dinoNameTag": "Basilosaurus",
			"customTag": "Harbinger",
			"targetingTeamName": "Carnivores_Low",
			"mass": 300,
			"dragWeight": 899,
			"flags": [
				"allowCarryFlyerDinos",
				"allowRiding",
				"canBeDragged",
				"canBeTorpid",
				"canDrag",
				"isCarnivore",
				"isWaterDino",
				"dieIfLeftWater",
				"isTameable"
			],
			"leveling": { "mutagenCost": 38 },
			"cloning": {
				"costBase": 925,
				"costLevel": 55,
				"timeBase": 6475,
				"timeLevel": 385
			},
			"falling": {
				"dmgMult": 80,
				"maxSpeed": 1550
			},
			"movementW": {
				"walk": { "base": 400, "sprint": 1200 },
				"swim": { "base": 400 }
			},
			"movementD": {
				"walk": { "base": 900, "sprint": 2700 },
				"swim": { "base": 900 }
			},
			"staminaRates": {
				"sprint": -20,
				"swimOrFly": -3
			},
			"attack": {
				"defaultDmg": 90,
				"defaultSwingRadius": 190,
				"attacks": [
					{ "name": "Bite", "interval": 0.4, "dmg": 90, "radius": 600, "stamina": 0 },
					{ "name": "SavageBite", "interval": 8, "dmg": 110, "radius": 600, "stamina": 0 },
					{ "name": "Roar", "interval": 10, "dmg": 0, "radius": 0, "stamina": 0 }
				]
			},
			"death": { "baseXP": 40 }
		},
		{
			"name": "Atlas Capuchin",
			"bp": "/Game/Mods/AtlasPort/Critter/Monkey/AMonkey_Character_BP.AMonkey_Character_BP_C",
			"dinoNameTag": "Monkey",
			"customTag": "Monkey",
			"targetingTeamName": "Herbivores_Medium_Aggressive",
			"mass": 80,
			"dragWeight": 25,
			"flags": [
				"canBeDragged",
				"canBeTorpid",
				"canDrag",
				"canMountOnHumans",
				"isTameable"
			],
			"leveling": { "mutagenCost": 24 },
			"cloning": {
				"costBase": 575,
				"costLevel": 27.5,
				"timeBase": 4025,
				"timeLevel": 192.5
			},
			"falling": {
				"dmgMult": 0,
				"maxSpeed": 1550
			},
			"movementW": {
				"walk": { "base": 60, "sprint": 540 },
				"swim": { "base": 300 }
			},
			"movementD": {
				"walk": { "base": 60, "sprint": 540 },
				"swim": { "base": 300 }
			},
			"staminaRates": {
				"sprint": -4,
				"swimOrFly": -3
			},
			"attack": {
				"defaultDmg": 10,
				"defaultSwingRadius": 50,
				"attacks": [
					{ "name": "Melee", "interval": 0.4, "dmg": 15, "radius": 95, "stamina": 0 },
					{
						"name": "ThrowPoop", "interval": 4, "dmg": 0, "radius": 0, "stamina": 0,
						"isProjectile": true
					}
				]
			},
			"death": { "baseXP": 2 }
		},
		{
			"name": "Naga",
			"bp": "/Game/Mods/AtlasPort/Critter/Naga/Naga_Character_bp.Naga_Character_bp_C",
			"dinoNameTag": "Titanboa",
			"customTag": "Naga",
			"targetingTeamName": "Carnivores_Medium",
			"mass": 400,
			"dragWeight": 300,
			"flags": [
				"allowMountedWeaponry",
				"allowRiding",
				"canBeDragged",
				"canBeTorpid",
				"canDrag",
				"isAmphibious",
				"isBigDino",
				"isCarnivore",
				"isTameable"
			],
			"falling": {
				"dmgMult": 80,
				"maxSpeed": 1550
			},
			"movementW": {
				"walk": { "base": 300, "sprint": 1800 },
				"swim": { "base": 900, "sprint": 5400 }
			},
			"movementD": {
				"walk": { "base": 300, "sprint": 1800 },
				"swim": { "base": 900, "sprint": 5400 }
			},
			"staminaRates": {
				"sprint": -40,
				"swimOrFly": -3
			},
			"attack": {
				"defaultDmg": 45,
				"defaultSwingRadius": 300,
				"attacks": [
					{ "name": "Bite", "interval": 0.4, "dmg": 30, "radius": 400, "stamina": 0 },
					{ "name": "Spittle", "interval": 10, "dmg": 0, "radius": 240, "stamina": 180 },
					{ "name": "Tails", "interval": 10, "dmg": 20, "radius": 450, "stamina": 50 },
					{ "name": "Rawr", "interval": 10, "dmg": 0, "radius": 0, "stamina": 0 }
				]
			},
			"death": { "baseXP": 30 }
		},
		{
			"name": "Aberrant Naga",
			"bp": "/Game/Mods/AtlasPort/Critter/Naga/Naga_Character_bp_Aberrant.Naga_Character_bp_Aberrant_C",
			"dinoNameTag": "Titanboa",
			"customTag": "Naga",
			"targetingTeamName": "Carnivores_Medium",
			"mass": 400,
			"dragWeight": 300,
			"flags": [
				"allowMountedWeaponry",
				"allowRiding",
				"canBeDragged",
				"canBeTorpid",
				"canDrag",
				"isAmphibious",
				"isBigDino",
				"isCarnivore",
				"isTameable"
			],
			"falling": {
				"dmgMult": 80,
				"maxSpeed": 1550
			},
			"movementW": {
				"walk": { "base": 300, "sprint": 1800 },
				"swim": { "base": 900, "sprint": 5400 }
			},
			"movementD": {
				"walk": { "base": 300, "sprint": 1800 },
				"swim": { "base": 900, "sprint": 5400 }
			},
			"staminaRates": {
				"sprint": -40,
				"swimOrFly": -3
			},
			"attack": {
				"defaultDmg": 45,
				"defaultSwingRadius": 300,
				"attacks": [
					{ "name": "Bite", "interval": 0.4, "dmg": 30, "radius": 400, "stamina": 0 },
					{ "name": "Spittle", "interval": 10, "dmg": 0, "radius": 240, "stamina": 180 },
					{ "name": "Tails", "interval": 10, "dmg": 20, "radius": 450, "stamina": 50 },
					{ "name": "Rawr", "interval": 10, "dmg": 0, "radius": 0, "stamina": 0 }
				]
			},
			"death": { "baseXP": 30 }
		},
		{
			"name": "Arcane Naga",
			"bp": "/Game/Mods/AtlasPort/Critter/Naga/Naga_Character_bp_Arcane.Naga_Character_bp_Arcane_C",
			"dinoNameTag": "Titanboa",
			"customTag": "Naga",
			"targetingTeamName": "Carnivores_Medium",
			"mass": 400,
			"dragWeight": 300,
			"flags": [
				"allowMountedWeaponry",
				"allowRiding",
				"canBeDragged",
				"canBeTorpid",
				"canDrag",
				"isAmphibious",
				"isBigDino",
				"isCarnivore",
				"isTameable"
			],
			"falling": {
				"dmgMult": 80,
				"maxSpeed": 1550
			},
			"movementW": {
				"walk": { "base": 300, "sprint": 1800 },
				"swim": { "base": 900, "sprint": 5400 }
			},
			"movementD": {
				"walk": { "base": 300, "sprint": 1800 },
				"swim": { "base": 900, "sprint": 5400 }
			},
			"staminaRates": {
				"sprint": -40,
				"swimOrFly": -3
			},
			"attack": {
				"defaultDmg": 45,
				"defaultSwingRadius": 300,
				"attacks": [
					{ "name": "Bite", "interval": 0.4, "dmg": 30, "radius": 400, "stamina": 0 },
					{ "name": "Spittle", "interval": 10, "dmg": 0, "radius": 240, "stamina": 180 },
					{ "name": "Tails", "interval": 10, "dmg": 20, "radius": 450, "stamina": 50 },
					{ "name": "Rawr", "interval": 10, "dmg": 0, "radius": 0, "stamina": 0 }
				]
			},
			"death": { "baseXP": 30 }
		},
		{
			"name": "Olfend",
			"bp": "/Game/Mods/AtlasPort/Critter/Olfend/Olfend_Character_BP.Olfend_Character_BP_C",
			"dinoNameTag": "Camelsaurus",
			"customTag": "Olfend",
			"targetingTeamName": "Herbivores_Medium",
			"mass": 380,
			"dragWeight": 150,
			"flags": [
				"allowMountedWeaponry",
				"allowRiding",
				"canBeDragged",
				"canBeTorpid",
				"canDrag",
				"isTameable"
			],
			"leveling": {
				"wildLevelTable": [ { "chance": 1, "min": 21, "max": 30 } ],
				"mutagenCost": 36
			},
			"cloning": {
				"costBase": 875,
				"costLevel": 55,
				"timeBase": 6125,
				"timeLevel": 385
			},
			"falling": {
				"dmgMult": 80,
				"maxSpeed": 1550
			},
			"movementW": {
				"walk": { "base": 325, "sprint": 1950 },
				"swim": { "base": 265 }
			},
			"movementD": {
				"walk": { "base": 325, "sprint": 1950 },
				"swim": { "base": 265 }
			},
			"staminaRates": {
				"sprint": -2.5,
				"swimOrFly": -3
			},
			"attack": {
				"defaultDmg": 13,
				"defaultSwingRadius": 185,
				"attacks": [
					{ "name": "None", "interval": 0.05, "dmg": 15, "radius": 280, "stamina": 0 },
					{ "name": "None", "interval": 4, "dmg": 25, "radius": 280, "stamina": 0 },
					{ "name": "None", "interval": 0.63, "dmg": 0, "radius": 0, "stamina": 0 }
				]
			},
			"death": { "baseXP": 4 }
		},
		{
			"name": "Ostrich",
			"bp": "/Game/Mods/AtlasPort/Critter/Ostrich/AOstrich_Character_BP.AOstrich_Character_BP_C",
			"dinoNameTag": "TerrorBird",
			"customTag": "Ostrich",
			"targetingTeamName": "Herbivores_Medium_Aggressive",
			"mass": 165,
			"dragWeight": 112,
			"flags": [
				"allowMountedWeaponry",
				"allowRiding",
				"canBeDragged",
				"canBeTorpid",
				"canDrag",
				"isTameable"
			],
			"leveling": { "mutagenCost": 24 },
			"cloning": {
				"costBase": 575,
				"costLevel": 55,
				"timeBase": 4025,
				"timeLevel": 385
			},
			"falling": {
				"dmgMult": 80,
				"maxSpeed": 1550
			},
			"movementW": {
				"walk": { "base": 320, "sprint": 1920 },
				"swim": { "base": 300 }
			},
			"movementD": {
				"walk": { "base": 320, "sprint": 1920 },
				"swim": { "base": 300 }
			},
			"staminaRates": {
				"sprint": -5,
				"swimOrFly": -3
			},
			"attack": {
				"defaultDmg": 15,
				"defaultSwingRadius": 65,
				"attacks": [
					{ "name": "Melee", "interval": 0.2, "dmg": 14, "radius": 240, "stamina": 0 },
					{ "name": "Melee", "interval": 0.2, "dmg": 0, "radius": 0, "stamina": 0 }
				]
			},
			"death": { "baseXP": 3 }
		},
		{
			"name": "Heracles",
			"bp": "/Game/Mods/AtlasPort/Critter/Parrot/AParrot_character_bp.AParrot_character_bp_C",
			"dinoNameTag": "Heracles",
			"customTag": "Parrot",
			"targetingTeamName": "Herbivores",
			"mass": 190,
			"dragWeight": 150,
			"flags": [
				"allowFlyerLandedRider",
				"allowRiding",
				"canBeDragged",
				"canBeTorpid",
				"canDrag",
				"isFlyerDino",
				"preventCharacterBasing",
				"isTameable"
			],
			"leveling": {
				"wildLevelTable": [ { "chance": 1, "min": 21, "max": 30 } ],
				"mutagenCost": 79
			},
			"cloning": {
				"costBase": 1975,
				"costLevel": 55,
				"timeBase": 13825,
				"timeLevel": 385
			},
			"falling": {
				"dmgMult": 80,
				"maxSpeed": 1550
			},
			"movementW": {
				"walk": { "base": 260, "sprint": 1040 },
				"fly": { "base": 900, "sprint": 1800 },
				"swim": { "base": 300 }
			},
			"movementD": {
				"walk": { "base": 260, "sprint": 1040 },
				"fly": { "base": 900, "sprint": 1800 },
				"swim": { "base": 300 }
			},
			"movementR": {
				"walk": { "base": 273, "sprint": 1092 },
				"fly": { "base": 945, "sprint": 1890 },
				"swim": { "base": 315 }
			},
			"staminaRates": {
				"sprint": -10,
				"swimOrFly": -3
			},
			"attack": {
				"defaultDmg": 15,
				"defaultSwingRadius": 200,
				"attacks": [
					{ "name": "Bite", "interval": 0.6, "dmg": 23, "radius": 240, "stamina": 0 },
					{ "name": "Drill Run", "interval": 0.6, "dmg": 0, "radius": 0, "stamina": 0 }
				]
			},
			"death": { "baseXP": 3 }
		},
		{
			"name": "Apophis Rattlesnake",
			"bp": "/Game/Mods/AtlasPort/Critter/Rattlesnake/ARattler_Character_bp.ARattler_Character_bp_C",
			"dinoNameTag": "Titanboa",
			"customTag": "Naga",
			"targetingTeamName": "Carnivores_Medium",
			"mass": 400,
			"dragWeight": 300,
			"flags": [
				"allowMountedWeaponry",
				"allowRiding",
				"canBeDragged",
				"canBeTorpid",
				"canDrag",
				"isAmphibious",
				"isBigDino",
				"isCarnivore",
				"isTameable"
			],
			"falling": {
				"dmgMult": 80,
				"maxSpeed": 1550
			},
			"movementW": {
				"walk": { "base": 300, "sprint": 1650 },
				"swim": { "base": 700 }
			},
			"movementD": {
				"walk": { "base": 300, "sprint": 1650 },
				"swim": { "base": 700 }
			},
			"staminaRates": {
				"sprint": -40,
				"swimOrFly": -3
			},
			"attack": {
				"defaultDmg": 45,
				"defaultSwingRadius": 300,
				"attacks": [
					{ "name": "BiteNomFury", "interval": 0.4, "dmg": 40, "radius": 400, "stamina": 0 },
					{ "name": "BiteNomFury", "interval": 0.4, "dmg": 0, "radius": 0, "stamina": 25 },
					{ "name": "BiteNomFury", "interval": 0.4, "dmg": 0, "radius": 0, "stamina": 0 }
				]
			},
			"death": { "baseXP": 30 }
		},
		{
			"name": "Alpha Razortooth",
			"bp": "/Game/Mods/AtlasPort/Critter/Razortooth/MegaRazortooth_Character_BP.MegaRazortooth_Character_BP_C",
			"dinoNameTag": "Yutyrannus",
			"customTag": "Razortooth",
			"targetingTeamName": "Carnivores_High",
			"mass": 5000,
			"dragWeight": 550,
			"flags": [
				"allowRiding",
				"canBeDragged",
				"canDrag",
				"doStepDamage",
				"isBigDino",
				"isCarnivore"
			],
			"leveling": { "mutagenCost": 94 },
			"cloning": {
				"costBase": 2350,
				"costLevel": 55,
				"timeBase": 16450,
				"timeLevel": 385
			},
			"falling": {
				"dmgMult": 80,
				"maxSpeed": 1550
			},
			"movementW": {
				"walk": { "base": 700, "sprint": 2450 }
			},
			"movementD": {
				"walk": { "base": 700, "sprint": 2450 }
			},
			"staminaRates": { "sprint": -35 },
			"attack": {
				"defaultDmg": 0,
				"defaultSwingRadius": 90,
				"attacks": [
					{ "name": "Bite", "interval": 0.4, "dmg": 150, "radius": 500, "stamina": 10 },
					{ "name": "Fear", "interval": 8, "dmg": 1, "radius": 1500, "stamina": 325 },
					{ "name": "Courage", "interval": 8, "dmg": 1, "radius": 1500, "stamina": 325 },
					{ "name": "None", "interval": 5, "dmg": 180, "radius": 500, "stamina": 0 }
				]
			},
			"death": {
				"lootBagChance": 1,
				"lootBags": [
					{
						"chance": 1,
						"item": "/Game/Mods/AtlasPort/Item/Loot/DinoDropInventoryComponent_AlphaAtlas.DinoDropInventoryComponent_AlphaAtlas"
					}
				],
				"baseXP": 30
			}
		},
		{
			"name": "Alpha Aberrant Razortooth",
			"bp": "/Game/Mods/AtlasPort/Critter/Razortooth/MegaRazortooth_Character_BP_Aberrant.MegaRazortooth_Character_BP_Aberrant_C",
			"dinoNameTag": "Yutyrannus",
			"customTag": "Razortooth",
			"targetingTeamName": "Carnivores_High",
			"mass": 5000,
			"dragWeight": 550,
			"flags": [
				"allowRiding",
				"canBeDragged",
				"canDrag",
				"doStepDamage",
				"isBigDino",
				"isCarnivore"
			],
			"leveling": { "mutagenCost": 94 },
			"cloning": {
				"costBase": 2350,
				"costLevel": 55,
				"timeBase": 16450,
				"timeLevel": 385
			},
			"falling": {
				"dmgMult": 80,
				"maxSpeed": 1550
			},
			"movementW": {
				"walk": { "base": 700, "sprint": 2450 }
			},
			"movementD": {
				"walk": { "base": 700, "sprint": 2450 }
			},
			"staminaRates": { "sprint": -35 },
			"attack": {
				"defaultDmg": 0,
				"defaultSwingRadius": 90,
				"attacks": [
					{ "name": "Bite", "interval": 0.4, "dmg": 150, "radius": 500, "stamina": 10 },
					{ "name": "Fear", "interval": 8, "dmg": 1, "radius": 1500, "stamina": 325 },
					{ "name": "Courage", "interval": 8, "dmg": 1, "radius": 1500, "stamina": 325 },
					{ "name": "None", "interval": 5, "dmg": 180, "radius": 500, "stamina": 0 }
				]
			},
			"death": {
				"lootBagChance": 1,
				"lootBags": [
					{
						"chance": 1,
						"item": "/Game/Mods/AtlasPort/Item/Loot/DinoDropInventoryComponent_AlphaAtlas.DinoDropInventoryComponent_AlphaAtlas"
					}
				],
				"baseXP": 30
			}
		},
		{
			"name": "Alpha Arcane Razortooth",
			"bp": "/Game/Mods/AtlasPort/Critter/Razortooth/MegaRazortooth_Character_BP_Arcane.MegaRazortooth_Character_BP_Arcane_C",
			"dinoNameTag": "Yutyrannus",
			"customTag": "Razortooth",
			"targetingTeamName": "Carnivores_High",
			"mass": 5000,
			"dragWeight": 550,
			"flags": [
				"allowRiding",
				"canBeDragged",
				"canDrag",
				"doStepDamage",
				"isBigDino",
				"isCarnivore"
			],
			"leveling": { "mutagenCost": 94 },
			"cloning": {
				"costBase": 2350,
				"costLevel": 55,
				"timeBase": 16450,
				"timeLevel": 385
			},
			"falling": {
				"dmgMult": 80,
				"maxSpeed": 1550
			},
			"movementW": {
				"walk": { "base": 700, "sprint": 2450 }
			},
			"movementD": {
				"walk": { "base": 700, "sprint": 2450 }
			},
			"staminaRates": { "sprint": -35 },
			"attack": {
				"defaultDmg": 0,
				"defaultSwingRadius": 90,
				"attacks": [
					{ "name": "Bite", "interval": 0.4, "dmg": 150, "radius": 500, "stamina": 10 },
					{ "name": "Fear", "interval": 8, "dmg": 1, "radius": 1500, "stamina": 325 },
					{ "name": "Courage", "interval": 8, "dmg": 1, "radius": 1500, "stamina": 325 },
					{ "name": "None", "interval": 5, "dmg": 180, "radius": 500, "stamina": 0 }
				]
			},
			"death": {
				"lootBagChance": 1,
				"lootBags": [
					{
						"chance": 1,
						"item": "/Game/Mods/AtlasPort/Item/Loot/DinoDropInventoryComponent_AlphaAtlas.DinoDropInventoryComponent_AlphaAtlas"
					}
				],
				"baseXP": 30
			}
		},
		{
			"name": "Razortooth",
			"bp": "/Game/Mods/AtlasPort/Critter/Razortooth/Razortooth_Character_BP.Razortooth_Character_BP_C",
			"dinoNameTag": "Yutyrannus",
			"customTag": "Razortooth",
			"targetingTeamName": "Carnivores_High",
			"mass": 5000,
			"dragWeight": 550,
			"flags": [
				"allowRiding",
				"canBeDragged",
				"canBeTorpid",
				"canDrag",
				"doStepDamage",
				"isBigDino",
				"isCarnivore",
				"isTameable"
			],
			"leveling": { "mutagenCost": 94 },
			"cloning": {
				"costBase": 2350,
				"costLevel": 55,
				"timeBase": 16450,
				"timeLevel": 385
			},
			"falling": {
				"dmgMult": 80,
				"maxSpeed": 1550
			},
			"movementW": {
				"walk": { "base": 700, "sprint": 2450 }
			},
			"movementD": {
				"walk": { "base": 700, "sprint": 2450 }
			},
			"staminaRates": { "sprint": -35 },
			"attack": {
				"defaultDmg": 0,
				"defaultSwingRadius": 90,
				"attacks": [
					{ "name": "Bite", "interval": 0.4, "dmg": 58, "radius": 500, "stamina": 10 },
					{ "name": "Fear", "interval": 8, "dmg": 1, "radius": 1500, "stamina": 325 },
					{ "name": "Courage", "interval": 8, "dmg": 1, "radius": 1500, "stamina": 325 },
					{ "name": "None", "interval": 5, "dmg": 80, "radius": 500, "stamina": 0 }
				]
			},
			"death": {
				"lootBagChance": 1,
				"lootBags": [
					{
						"chance": 1,
						"item": "/Game/PrimalEarth/CoreBlueprints/Inventories/DinoDropInventoryComponent_Carnivore_Huge_Yuty.DinoDropInventoryComponent_Carnivore_Huge_Yuty"
					}
				],
				"baseXP": 30
			}
		},
		{
			"name": "Aberrant Razortooth",
			"bp": "/Game/Mods/AtlasPort/Critter/Razortooth/Razortooth_Character_BP_Aberrant.Razortooth_Character_BP_Aberrant_C",
			"dinoNameTag": "Yutyrannus",
			"customTag": "Razortooth",
			"targetingTeamName": "Carnivores_High",
			"mass": 5000,
			"dragWeight": 550,
			"flags": [
				"allowRiding",
				"canBeDragged",
				"canBeTorpid",
				"canDrag",
				"doStepDamage",
				"isBigDino",
				"isCarnivore",
				"isTameable"
			],
			"leveling": { "mutagenCost": 94 },
			"cloning": {
				"costBase": 2350,
				"costLevel": 55,
				"timeBase": 16450,
				"timeLevel": 385
			},
			"falling": {
				"dmgMult": 80,
				"maxSpeed": 1550
			},
			"movementW": {
				"walk": { "base": 700, "sprint": 2450 }
			},
			"movementD": {
				"walk": { "base": 700, "sprint": 2450 }
			},
			"staminaRates": { "sprint": -35 },
			"attack": {
				"defaultDmg": 0,
				"defaultSwingRadius": 90,
				"attacks": [
					{ "name": "Bite", "interval": 0.4, "dmg": 58, "radius": 500, "stamina": 10 },
					{ "name": "Fear", "interval": 8, "dmg": 1, "radius": 1500, "stamina": 325 },
					{ "name": "Courage", "interval": 8, "dmg": 1, "radius": 1500, "stamina": 325 },
					{ "name": "None", "interval": 5, "dmg": 80, "radius": 500, "stamina": 0 }
				]
			},
			"death": {
				"lootBagChance": 1,
				"lootBags": [
					{
						"chance": 1,
						"item": "/Game/PrimalEarth/CoreBlueprints/Inventories/DinoDropInventoryComponent_Carnivore_Huge_Yuty.DinoDropInventoryComponent_Carnivore_Huge_Yuty"
					}
				],
				"baseXP": 30
			}
		},
		{
			"name": "Arcane Razortooth",
			"bp": "/Game/Mods/AtlasPort/Critter/Razortooth/Razortooth_Character_BP_Arcane.Razortooth_Character_BP_Arcane_C",
			"dinoNameTag": "Yutyrannus",
			"customTag": "Razortooth",
			"targetingTeamName": "Carnivores_High",
			"mass": 5000,
			"dragWeight": 550,
			"flags": [
				"allowRiding",
				"canBeDragged",
				"canBeTorpid",
				"canDrag",
				"doStepDamage",
				"isBigDino",
				"isCarnivore",
				"isTameable"
			],
			"leveling": { "mutagenCost": 94 },
			"cloning": {
				"costBase": 2350,
				"costLevel": 55,
				"timeBase": 16450,
				"timeLevel": 385
			},
			"falling": {
				"dmgMult": 80,
				"maxSpeed": 1550
			},
			"movementW": {
				"walk": { "base": 700, "sprint": 2450 }
			},
			"movementD": {
				"walk": { "base": 700, "sprint": 2450 }
			},
			"staminaRates": { "sprint": -35 },
			"attack": {
				"defaultDmg": 0,
				"defaultSwingRadius": 90,
				"attacks": [
					{ "name": "Bite", "interval": 0.4, "dmg": 58, "radius": 500, "stamina": 10 },
					{ "name": "Fear", "interval": 8, "dmg": 1, "radius": 1500, "stamina": 325 },
					{ "name": "Courage", "interval": 8, "dmg": 1, "radius": 1500, "stamina": 325 },
					{ "name": "None", "interval": 5, "dmg": 80, "radius": 500, "stamina": 0 }
				]
			},
			"death": {
				"lootBagChance": 1,
				"lootBags": [
					{
						"chance": 1,
						"item": "/Game/PrimalEarth/CoreBlueprints/Inventories/DinoDropInventoryComponent_Carnivore_Huge_Yuty.DinoDropInventoryComponent_Carnivore_Huge_Yuty"
					}
				],
				"baseXP": 30
			}
		},
		{
			"name": "Pangolin Rhinoceros",
			"bp": "/Game/Mods/AtlasPort/Critter/Rhino/ARhino_Character_BP.ARhino_Character_BP_C",
			"dinoNameTag": "PagRhino",
			"customTag": "PagRhino",
			"targetingTeamName": "Herbivores_Medium",
			"mass": 330,
			"dragWeight": 375,
			"flags": [
				"allowMountedWeaponry",
				"allowRiding",
				"canBeDragged",
				"canBeTorpid",
				"canDrag",
				"doStepDamage",
				"isBigDino",
				"isTameable"
			],
			"leveling": { "mutagenCost": 40 },
			"cloning": {
				"costBase": 975,
				"costLevel": 55,
				"timeBase": 6825,
				"timeLevel": 385
			},
			"falling": {
				"dmgMult": 80,
				"maxSpeed": 1550
			},
			"movementW": {
				"walk": { "base": 150, "sprint": 1500 },
				"swim": { "base": 300 }
			},
			"movementD": {
				"walk": { "base": 150, "sprint": 1500 },
				"swim": { "base": 300 }
			},
			"staminaRates": {
				"sprint": -14,
				"swimOrFly": -3
			},
			"attack": {
				"defaultDmg": 40,
				"defaultSwingRadius": 430,
				"attacks": [
					{ "name": "Horn", "interval": 0.22, "dmg": 35, "radius": 430, "stamina": 0 },
					{ "name": "Bite", "interval": 5, "dmg": 25, "radius": 430, "stamina": 0 }
				]
			},
			"death": {
				"lootBagChance": 1,
				"lootBags": [
					{
						"chance": 1,
						"item": "/Game/PrimalEarth/CoreBlueprints/Inventories/DinoDropInventoryComponent_Rhino.DinoDropInventoryComponent_Rhino"
					}
				],
				"baseXP": 4
			}
		},
		{
			"name": "Tyrant Scorpion",
			"bp": "/Game/Mods/AtlasPort/Critter/Scorpion/AScorpion_Character_BP.AScorpion_Character_BP_C",
			"dinoNameTag": "Scorpion",
			"customTag": "AScorpion",
			"targetingTeamName": "Carnivores_Medium",
			"mass": 120,
			"dragWeight": 280,
			"flags": [
				"allowMountedWeaponry",
				"allowRiding",
				"canBeDragged",
				"canBeTorpid",
				"canDrag",
				"isCarnivore",
				"isTameable"
			],
			"leveling": { "mutagenCost": 33 },
			"cloning": {
				"costBase": 800,
				"costLevel": 55,
				"timeBase": 5600,
				"timeLevel": 385
			},
			"falling": {
				"dmgMult": 80,
				"maxSpeed": 1550
			},
			"movementW": {
				"walk": { "base": 360, "sprint": 864 },
				"swim": { "base": 300 }
			},
			"movementD": {
				"walk": { "base": 360, "sprint": 864 },
				"swim": { "base": 300 }
			},
			"staminaRates": {
				"sprint": -7,
				"swimOrFly": -3
			},
			"attack": {
				"defaultDmg": 20,
				"defaultSwingRadius": 160,
				"attacks": [
					{ "name": "Claws", "interval": 0.1, "dmg": 25, "radius": 250, "stamina": 0 },
					{ "name": "VenomStab", "interval": 5, "dmg": 35, "radius": 250, "stamina": 0 },
					{ "name": "Taunt", "interval": 5, "dmg": 0, "radius": 0, "stamina": 0 },
					{ "name": "HeldSting", "interval": 15, "dmg": 64, "radius": 250, "stamina": 0 },
					{ "name": "SlamThrow", "interval": 25, "dmg": 25, "radius": 115, "stamina": 100 }
				]
			},
			"death": {
				"lootBagChance": 0.3,
				"lootBags": [
					{
						"chance": 1,
						"item": "/Game/PrimalEarth/CoreBlueprints/Inventories/DinoDropInventoryComponent_Carnivore_Medium.DinoDropInventoryComponent_Carnivore_Medium"
					}
				],
				"baseXP": 6
			}
		},
		{
			"name": "Arcane Tyrant Scorpion",
			"bp": "/Game/Mods/AtlasPort/Critter/Scorpion/AScorpion_Character_BP_Arcane.AScorpion_Character_BP_Arcane_C",
			"dinoNameTag": "Scorpion",
			"customTag": "AScorpion",
			"targetingTeamName": "Carnivores_Medium",
			"mass": 120,
			"dragWeight": 280,
			"flags": [
				"allowMountedWeaponry",
				"allowRiding",
				"canBeDragged",
				"canBeTorpid",
				"canDrag",
				"isCarnivore",
				"isTameable"
			],
			"leveling": { "mutagenCost": 33 },
			"cloning": {
				"costBase": 800,
				"costLevel": 55,
				"timeBase": 5600,
				"timeLevel": 385
			},
			"falling": {
				"dmgMult": 80,
				"maxSpeed": 1550
			},
			"movementW": {
				"walk": { "base": 360, "sprint": 864 },
				"swim": { "base": 300 }
			},
			"movementD": {
				"walk": { "base": 360, "sprint": 864 },
				"swim": { "base": 300 }
			},
			"staminaRates": {
				"sprint": -7,
				"swimOrFly": -3
			},
			"attack": {
				"defaultDmg": 20,
				"defaultSwingRadius": 160,
				"attacks": [
					{ "name": "Claws", "interval": 0.1, "dmg": 25, "radius": 250, "stamina": 0 },
					{ "name": "VenomStab", "interval": 5, "dmg": 35, "radius": 250, "stamina": 0 },
					{ "name": "Taunt", "interval": 5, "dmg": 0, "radius": 0, "stamina": 0 },
					{ "name": "HeldSting", "interval": 15, "dmg": 64, "radius": 250, "stamina": 0 },
					{ "name": "SlamThrow", "interval": 25, "dmg": 25, "radius": 115, "stamina": 100 }
				]
			},
			"death": {
				"lootBagChance": 0.3,
				"lootBags": [
					{
						"chance": 1,
						"item": "/Game/PrimalEarth/CoreBlueprints/Inventories/DinoDropInventoryComponent_Carnivore_Medium.DinoDropInventoryComponent_Carnivore_Medium"
					}
				],
				"baseXP": 6
			}
		},
		{
			"name": "Hippocampus",
			"bp": "/Game/Mods/AtlasPort/Critter/Seahorse/Hippocampus_Character_bp.Hippocampus_Character_bp_C",
			"dinoNameTag": "Equus",
			"customTag": "Hippocampus",
			"targetingTeamName": "Carnivore_Water",
			"mass": 300,
			"dragWeight": 250,
			"flags": [
				"allowCarryFlyerDinos",
				"allowMountedWeaponry",
				"allowRiding",
				"canBeDragged",
				"canBeTorpid",
				"canDrag",
				"isWaterDino",
				"dieIfLeftWater",
				"isTameable"
			],
			"leveling": { "mutagenCost": 38 },
			"cloning": {
				"costBase": 925,
				"costLevel": 55,
				"timeBase": 6475,
				"timeLevel": 385
			},
			"falling": {
				"dmgMult": 80,
				"maxSpeed": 1550
			},
			"movementW": {
				"walk": { "base": 1000, "sprint": 4600 },
				"swim": { "base": 800 }
			},
			"movementD": {
				"walk": { "base": 1000, "sprint": 4600 },
				"swim": { "base": 800 }
			},
			"staminaRates": {
				"sprint": -2,
				"swimOrFly": -3
			},
			"attack": {
				"defaultDmg": 40,
				"defaultSwingRadius": 170,
				"attacks": [
					{ "name": "Bite", "interval": 0.2, "dmg": 32, "radius": 320, "stamina": 0 },
					{ "name": "Proj", "interval": 15, "dmg": 0, "radius": 320, "stamina": 120 }
				]
			},
			"death": { "baseXP": 12 }
		},
		{
			"name": "Hippocampus",
			"bp": "/Game/Mods/AtlasPort/Critter/Seahorse/Hippocampus_Character_bp_Herbivore.Hippocampus_Character_bp_Herbivore_C",
			"dinoNameTag": "Equus",
			"customTag": "Hippocampus",
			"targetingTeamName": "Carnivore_Water",
			"mass": 300,
			"dragWeight": 250,
			"flags": [
				"allowCarryFlyerDinos",
				"allowMountedWeaponry",
				"allowRiding",
				"canBeDragged",
				"canBeTorpid",
				"canDrag",
				"isWaterDino",
				"dieIfLeftWater",
				"isTameable"
			],
			"leveling": { "mutagenCost": 38 },
			"cloning": {
				"costBase": 925,
				"costLevel": 55,
				"timeBase": 6475,
				"timeLevel": 385
			},
			"falling": {
				"dmgMult": 80,
				"maxSpeed": 1550
			},
			"movementW": {
				"walk": { "base": 1000, "sprint": 4600 },
				"swim": { "base": 800 }
			},
			"movementD": {
				"walk": { "base": 1000, "sprint": 4600 },
				"swim": { "base": 800 }
			},
			"staminaRates": {
				"sprint": -2,
				"swimOrFly": -3
			},
			"attack": {
				"defaultDmg": 40,
				"defaultSwingRadius": 170,
				"attacks": [
					{ "name": "Bite", "interval": 0.2, "dmg": 32, "radius": 320, "stamina": 0 },
					{ "name": "Proj", "interval": 15, "dmg": 0, "radius": 320, "stamina": 120 }
				]
			},
			"death": { "baseXP": 12 }
		},
		{
			"name": "Shieldhorn",
			"bp": "/Game/Mods/AtlasPort/Critter/ShieldHorn/Shieldhorn_Character_BP.Shieldhorn_Character_bp_C",
			"dinoNameTag": "Trike",
			"customTag": "Trike",
			"targetingTeamName": "Herbivores_Large_Aggressive",
			"mass": 400,
			"dragWeight": 350,
			"flags": [
				"allowMountedWeaponry",
				"allowRiding",
				"canBeDragged",
				"canBeTorpid",
				"canDrag",
				"isBigDino",
				"isTameable"
			],
			"falling": {
				"dmgMult": 80,
				"maxSpeed": 1550
			},
			"movementW": {
				"walk": { "base": 250, "sprint": 1500 },
				"swim": { "base": 300 }
			},
			"movementD": {
				"walk": { "base": 250, "sprint": 1500 },
				"swim": { "base": 300 }
			},
			"staminaRates": {
				"sprint": -14,
				"swimOrFly": -3
			},
			"attack": {
				"defaultDmg": 45,
				"defaultSwingRadius": 300,
				"attacks": [
					{ "name": "Horns", "interval": 0.4, "dmg": 43, "radius": 400, "stamina": 0 },
					{ "name": "Stomp", "interval": 5, "dmg": 50, "radius": 450, "stamina": 0 },
					{ "name": "BiteNomFury", "interval": 0.4, "dmg": 0, "radius": 0, "stamina": 0 }
				]
			},
			"death": { "baseXP": 30 }
		},
		{
			"name": "Allseer Squid",
			"bp": "/Game/Mods/AtlasPort/Critter/Squid/AtlasSquid_Character_BP.AtlasSquid_Character_BP_C",
			"dinoNameTag": "AtlasSquid",
			"customTag": "Tusoteuthis",
			"targetingTeamName": "Carnivore_Water",
			"mass": 300,
			"dragWeight": 1500,
			"flags": [
				"allowRiding",
				"canBeDragged",
				"canDrag",
				"isBigDino",
				"isCarnivore",
				"isWaterDino",
				"dieIfLeftWater",
				"isTameable"
			],
			"leveling": { "mutagenCost": 87 },
			"cloning": {
				"costBase": 2175,
				"costLevel": 55,
				"timeBase": 15225,
				"timeLevel": 385
			},
			"falling": {
				"dmgMult": 80,
				"maxSpeed": 1550
			},
			"movementW": {
				"walk": { "base": 5000, "sprint": 25000 },
				"swim": { "base": 600 }
			},
			"movementD": {
				"walk": { "base": 5000, "sprint": 25000 },
				"swim": { "base": 600 }
			},
			"movementR": {
				"walk": { "base": 5000, "sprint": 22500 },
				"swim": { "base": 600 }
			},
			"staminaRates": {
				"sprint": -10,
				"swimOrFly": -3
			},
			"attack": {
				"defaultDmg": 0,
				"defaultSwingRadius": 1200,
				"attacks": [
					{ "name": "Tentaslap", "interval": 0, "dmg": 45, "radius": 1200, "stamina": 10 },
					{ "name": "Grab Prey", "interval": 1.5, "dmg": 15, "radius": 1200, "stamina": 25 },
					{
						"name": "Ink", "interval": 60, "dmg": 0, "radius": 0, "stamina": 50,
						"isProjectile": true
					},
					{ "name": "Crush Prey", "interval": 0, "dmg": 55, "radius": 0, "stamina": 10 }
				]
			},
			"death": {
				"lootBagChance": 1,
				"lootBags": [
					{
						"chance": 1,
						"item": "/Game/PrimalEarth/Dinos/Tusoteuthis/DinoDropInventoryComponent_Carnivore_Tusoteuthis.DinoDropInventoryComponent_Carnivore_Tusoteuthis"
					}
				],
				"baseXP": 100
			}
		},
		{
			"name": "Atlas Tiger",
			"bp": "/Game/Mods/AtlasPort/Critter/Tiger/ATiger_Character_BP.ATiger_Character_BP_C",
			"dinoNameTag": "Thylacoleo",
			"customTag": "ATiger",
			"targetingTeamName": "Carnivores_Medium",
			"mass": 330,
			"dragWeight": 200,
			"flags": [
				"allowMountedWeaponry",
				"allowRiding",
				"canBeDragged",
				"canBeTorpid",
				"canDrag",
				"isBigDino",
				"isCarnivore",
				"isTameable"
			],
			"leveling": {
				"wildLevelTable": [
					{ "chance": 0.8, "min": 13, "max": 20 },
					{ "chance": 0.2, "min": 21, "max": 30 }
				],
				"mutagenCost": 67
			},
			"cloning": {
				"costBase": 1675,
				"costLevel": 55,
				"timeBase": 11725,
				"timeLevel": 385
			},
			"falling": {
				"dmgMult": 80,
				"maxSpeed": 1550
			},
			"movementW": {
				"walk": { "base": 245, "sprint": 2100 },
				"swim": { "base": 420 }
			},
			"movementD": {
				"walk": { "base": 350, "sprint": 2100 },
				"swim": { "base": 600 }
			},
			"staminaRates": {
				"sprint": -7,
				"swimOrFly": -3
			},
			"attack": {
				"defaultDmg": 45,
				"defaultSwingRadius": 260,
				"attacks": [
					{ "name": "Bite", "interval": 0.1, "dmg": 40, "radius": 430, "stamina": 0 },
					{ "name": "Claw", "interval": 5, "dmg": 34, "radius": 430, "stamina": 0 },
					{ "name": "Pounce", "interval": 10, "dmg": 34, "radius": 430, "stamina": 150 },
					{ "name": "Maul", "interval": 10, "dmg": 34, "radius": 430, "stamina": 0 },
					{ "name": "Maul", "interval": 10, "dmg": 9, "radius": 9, "stamina": 0 }
				]
			},
			"death": {
				"lootBagChance": 0.3,
				"lootBags": [
					{
						"chance": 1,
						"item": "/Game/PrimalEarth/CoreBlueprints/Inventories/DinoDropInventoryComponent_Carnivore_Medium.DinoDropInventoryComponent_Carnivore_Medium"
					}
				],
				"baseXP": 4
			}
		},
		{
			"name": "Arcane Atlas Tiger",
			"bp": "/Game/Mods/AtlasPort/Critter/Tiger/ATiger_Character_BP_Arcane.ATiger_Character_BP_Arcane_C",
			"dinoNameTag": "Thylacoleo",
			"customTag": "ATiger",
			"targetingTeamName": "Carnivores_Medium",
			"mass": 330,
			"dragWeight": 200,
			"flags": [
				"allowMountedWeaponry",
				"allowRiding",
				"canBeDragged",
				"canBeTorpid",
				"canDrag",
				"isBigDino",
				"isCarnivore",
				"isTameable"
			],
			"leveling": {
				"wildLevelTable": [
					{ "chance": 0.8, "min": 13, "max": 20 },
					{ "chance": 0.2, "min": 21, "max": 30 }
				],
				"mutagenCost": 67
			},
			"cloning": {
				"costBase": 1675,
				"costLevel": 55,
				"timeBase": 11725,
				"timeLevel": 385
			},
			"falling": {
				"dmgMult": 80,
				"maxSpeed": 1550
			},
			"movementW": {
				"walk": { "base": 245, "sprint": 2100 },
				"swim": { "base": 420 }
			},
			"movementD": {
				"walk": { "base": 350, "sprint": 2100 },
				"swim": { "base": 600 }
			},
			"staminaRates": {
				"sprint": -7,
				"swimOrFly": -3
			},
			"attack": {
				"defaultDmg": 45,
				"defaultSwingRadius": 260,
				"attacks": [
					{ "name": "Bite", "interval": 0.1, "dmg": 40, "radius": 430, "stamina": 0 },
					{ "name": "Claw", "interval": 5, "dmg": 34, "radius": 430, "stamina": 0 },
					{ "name": "Pounce", "interval": 10, "dmg": 34, "radius": 430, "stamina": 150 },
					{ "name": "Maul", "interval": 10, "dmg": 34, "radius": 430, "stamina": 0 },
					{ "name": "Maul", "interval": 10, "dmg": 9, "radius": 9, "stamina": 0 }
				]
			},
			"death": {
				"lootBagChance": 0.3,
				"lootBags": [
					{
						"chance": 1,
						"item": "/Game/PrimalEarth/CoreBlueprints/Inventories/DinoDropInventoryComponent_Carnivore_Medium.DinoDropInventoryComponent_Carnivore_Medium"
					}
				],
				"baseXP": 4
			}
		},
		{
			"name": "Grand Tortugar",
			"bp": "/Game/Mods/AtlasPort/Critter/Tortugar/Tortugar_Character_bp.Tortugar_Character_bp_C",
			"dinoNameTag": "Turtle",
			"customTag": "Tortugar",
			"targetingTeamName": "Herbivores_Large_Aggressive",
			"mass": 400,
			"dragWeight": 550,
			"flags": [
				"allowMountedWeaponry",
				"allowRiding",
				"canBeDragged",
				"canBeTorpid",
				"canDrag",
				"isBigDino",
				"isCarnivore",
				"isWaterDino",
				"isTameable"
			],
			"falling": {
				"dmgMult": 80,
				"maxSpeed": 1550
			},
			"movementW": {
				"walk": { "base": 400, "sprint": 1000 },
				"swim": { "base": 1000, "sprint": 2500 }
			},
			"movementD": {
				"walk": { "base": 400, "sprint": 1000 },
				"swim": { "base": 1000, "sprint": 2500 }
			},
			"staminaRates": {
				"sprint": -14,
				"swimOrFly": -3
			},
			"attack": {
				"defaultDmg": 0,
				"defaultSwingRadius": 300,
				"attacks": [
					{ "name": "Bite", "interval": 0.05, "dmg": 65, "radius": 620, "stamina": 0 },
					{ "name": "HeadButt", "interval": 3, "dmg": 55, "radius": 625, "stamina": 0 },
					{ "name": "Tail", "interval": 7, "dmg": 67, "radius": 500, "stamina": 0 },
					{ "name": "ShellOpenClose", "interval": 0.05, "dmg": 0, "radius": 0, "stamina": 0 },
					{ "name": "Roar", "interval": 0.05, "dmg": 0, "radius": 0, "stamina": 0 }
				]
			},
			"death": { "baseXP": 15 }
		},
		{
			"name": "Gargantuna",
			"bp": "/Game/Mods/AtlasPort/Critter/Tuna/ATuna_Character_BP.ATuna_Character_BP_C",
			"dinoNameTag": "Coel",
			"customTag": "",
			"targetingTeamName": "Herbivore_Water",
			"mass": 100,
			"dragWeight": 25,
			"flags": [
				"canBeDragged",
				"canDrag",
				"isWaterDino",
				"dieIfLeftWater",
				"isTameable",
				"canBeWildTrappedWithFishBasket",
				"canBeTamedWithFishBasket"
			],
			"falling": {
				"dmgMult": 80,
				"maxSpeed": 1550
			},
			"movementW": {
				"walk": { "base": 120, "sprint": 600 },
				"swim": { "base": 150 }
			},
			"movementD": {
				"walk": { "base": 120, "sprint": 600 },
				"swim": { "base": 150 }
			},
			"staminaRates": {
				"sprint": -19,
				"swimOrFly": -3
			},
			"attack": {
				"defaultDmg": 5,
				"defaultSwingRadius": 67,
				"attacks": [ { "name": "None", "interval": 1, "dmg": 5, "radius": 67, "stamina": 0 } ]
			},
			"death": { "baseXP": 0.5 }
		},
		{
			"name": "Yakalo",
			"bp": "/Game/Mods/AtlasPort/Critter/Yak/AYak_Character_BP.AYak_Character_BP_C",
			"dinoNameTag": "Phiomia",
			"customTag": "CowYak",
			"targetingTeamName": "Herbivores_Medium_Aggressive",
			"mass": 340,
			"dragWeight": 200,
			"flags": [
				"allowRiding",
				"canBeDragged",
				"canBeTorpid",
				"canDrag",
				"doStepDamage",
				"isBigDino",
				"isTameable"
			],
			"leveling": { "mutagenCost": 62 },
			"cloning": {
				"costBase": 1550,
				"costLevel": 55,
				"timeBase": 10850,
				"timeLevel": 385
			},
			"falling": {
				"dmgMult": 80,
				"maxSpeed": 1550
			},
			"movementW": {
				"walk": { "base": 350, "sprint": 2100 },
				"swim": { "base": 480 }
			},
			"movementD": {
				"walk": { "base": 350, "sprint": 2100 },
				"swim": { "base": 480 }
			},
			"staminaRates": {
				"sprint": -14,
				"swimOrFly": -3
			},
			"attack": {
				"defaultDmg": 42,
				"defaultSwingRadius": 500,
				"attacks": [ { "name": "Horn Attacks", "interval": 0.3, "dmg": 25, "radius": 420, "stamina": 0 } ]
			},
			"death": { "baseXP": 8 }
		},
		{
			"name": "Polar Yakalo",
			"bp": "/Game/Mods/AtlasPort/Critter/Yak/AYak_Character_BP_Polar.AYak_Character_BP_Polar_C",
			"dinoNameTag": "Phiomia",
			"customTag": "CowYak",
			"targetingTeamName": "Herbivores_Medium_Aggressive",
			"mass": 340,
			"dragWeight": 200,
			"flags": [
				"allowRiding",
				"canBeDragged",
				"canBeTorpid",
				"canDrag",
				"doStepDamage",
				"isBigDino",
				"isTameable"
			],
			"leveling": { "mutagenCost": 62 },
			"cloning": {
				"costBase": 1550,
				"costLevel": 55,
				"timeBase": 10850,
				"timeLevel": 385
			},
			"falling": {
				"dmgMult": 80,
				"maxSpeed": 1550
			},
			"movementW": {
				"walk": { "base": 350, "sprint": 2100 },
				"swim": { "base": 480 }
			},
			"movementD": {
				"walk": { "base": 350, "sprint": 2100 },
				"swim": { "base": 480 }
			},
			"staminaRates": {
				"sprint": -14,
				"swimOrFly": -3
			},
			"attack": {
				"defaultDmg": 42,
				"defaultSwingRadius": 500,
				"attacks": [ { "name": "Horn Attacks", "interval": 0.3, "dmg": 25, "radius": 420, "stamina": 0 } ]
			},
			"death": { "baseXP": 8 }
		},
		{
			"name": "Skeletal Rex",
			"bp": "/Game/Mods/AtlasPort/PrimalEarth/Dinos/Rex/Bone_MegaRex_Character_BP.Bone_MegaRex_Character_BP_C",
			"dinoNameTag": "Bone Rex",
			"customTag": "Rex",
			"targetingTeamName": "Carnivores_High",
			"mass": 400,
			"dragWeight": 550,
			"flags": [
				"allowRiding",
				"canBeDragged",
				"canDrag",
				"doStepDamage",
				"isBigDino",
				"isCarnivore"
			],
			"leveling": { "mutagenCost": 87 },
			"cloning": {
				"costBase": 2175,
				"costLevel": 55,
				"timeBase": 15225,
				"timeLevel": 385
			},
			"falling": {
				"dmgMult": 80,
				"maxSpeed": 1550
			},
			"movementW": {
				"walk": { "base": 755, "sprint": 1079.6 },
				"swim": { "base": 300 }
			},
			"movementD": {
				"walk": { "base": 755, "sprint": 1619.5 },
				"swim": { "base": 300 }
			},
			"staminaRates": {
				"sprint": -40,
				"swimOrFly": -3
			},
			"attack": {
				"defaultDmg": 170,
				"defaultSwingRadius": 450,
				"attacks": [
					{ "name": "None", "interval": 0.3, "dmg": 170, "radius": 450, "stamina": 0 },
					{ "name": "None", "interval": 0.5, "dmg": 0, "radius": 0, "stamina": 0 }
				]
			},
			"death": {
				"lootBagChance": 1,
				"lootBags": [
					{
						"chance": 1,
						"item": "/Game/Mods/AtlasPort/PrimalEarth/CoreBlueprints/Inventories/DinoDropInventoryComponent_Carnivore_Mega_Rex_Bone.DinoDropInventoryComponent_Carnivore_Mega_Rex_Bone"
					}
				],
				"baseXP": 885
			}
		},
		{
			"name": "Skeletal Bronto",
			"bp": "/Game/Mods/AtlasPort/PrimalEarth/Dinos/Sauropod/Bone_Sauropod_Character_BP.Bone_Sauropod_Character_BP_C",
			"dinoNameTag": "Bronto",
			"customTag": "Bronto",
			"targetingTeamName": "Herbivores_Large",
			"mass": 500,
			"dragWeight": 1000,
			"flags": [
				"allowRiding",
				"canBeDragged",
				"canBeTorpid",
				"canDrag",
				"doStepDamage",
				"isBigDino"
			],
			"leveling": { "mutagenCost": 79 },
			"cloning": {
				"costBase": 1975,
				"costLevel": 55,
				"timeBase": 13825,
				"timeLevel": 385
			},
			"falling": {
				"dmgMult": 80,
				"maxSpeed": 1550
			},
			"movementW": {
				"walk": { "base": 150, "sprint": 607.5 },
				"swim": { "base": 300 }
			},
			"movementD": {
				"walk": { "base": 180, "sprint": 405 },
				"swim": { "base": 360 }
			},
			"staminaRates": {
				"sprint": -20,
				"swimOrFly": -3
			},
			"attack": {
				"defaultDmg": 90,
				"defaultSwingRadius": 1000,
				"attacks": [ { "name": "melee", "interval": 1.2, "dmg": 90, "radius": 1000, "stamina": 0 } ]
			},
			"death": {
				"lootBagChance": 1,
				"lootBags": [
					{
						"chance": 1,
						"item": "/Game/Mods/AtlasPort/PrimalEarth/CoreBlueprints/Inventories/DinoDropInventoryComponent_Carnivore_Huge_Sauro_Bone.DinoDropInventoryComponent_Carnivore_Huge_Sauro_Bone"
					}
				],
				"baseXP": 22
			}
		},
		{
			"name": "Submarine",
			"bp": "/Game/Mods/AtlasPort/Submarine/AtlasSubmarine_BP.AtlasSubmarine_BP_C",
			"dinoNameTag": "Mek",
			"customTag": "Submarine",
			"targetingTeamName": "Carnivore_Water",
			"mass": 300,
			"dragWeight": 550,
			"flags": [
				"allowCarryFlyerDinos",
				"allowRiding",
				"canBeDragged",
				"canDrag",
				"isCarnivore",
				"isRobot",
				"isWaterDino",
				"dieIfLeftWater"
			],
			"leveling": {
				"wildLevelTable": [ { "chance": 1, "min": 30, "max": 30 } ]
			},
			"falling": {
				"dmgMult": 80,
				"maxSpeed": 1550
			},
			"movementW": {
				"walk": { "base": 1000, "sprint": 3500 },
				"swim": { "base": 800, "sprint": 2800 }
			},
			"movementD": {
				"walk": { "base": 1000, "sprint": 3500 },
				"swim": { "base": 800, "sprint": 2800 }
			},
			"staminaRates": {
				"sprint": -30,
				"swimOrFly": -3
			},
			"attack": {
				"defaultDmg": 40,
				"defaultSwingRadius": 170,
				"attacks": [
					{ "name": "None", "interval": 0.2, "dmg": 48, "radius": 460, "stamina": 0 },
					{ "name": "None", "interval": 0.2, "dmg": 48, "radius": 460, "stamina": 0 },
					{ "name": "None", "interval": 0.2, "dmg": 0, "radius": 0, "stamina": 0 },
					{ "name": "None", "interval": 0.2, "dmg": 0, "radius": 0, "stamina": 100 },
					{ "name": "None", "interval": 0.2, "dmg": 0, "radius": 0, "stamina": 200 }
				]
			},
			"death": { "baseXP": 12 }
		}
	]
}