{
	"version": "356.5.1611951166",
	"format": "1.14-flyerspeed",
	"mod": {
		"id": "2362246280",
		"tag": "GigaFullTame",
		"title": "Giga Full Tame"
	},
	"species": [
		{
			"name": "Tek Giganotosaurus",
			"blueprintPath": "/Game/Mods/GigaFullTame/BionicGigantFullTame_Character_BP.BionicGigantFullTame_Character_BP",
			"fullStatsRaw": [
				[ 80000, 0.0005, 0.002, 0, 0 ],
				[ 400, 0.0005, 0.01, 0, 0 ],
				[ 10000, 0.06, 0, 0, 0 ],
				[ 150, 0.0025, 0.025, 0, 0 ],
				[ 4000, 0.0025, 0.025, 0, 0 ],
				null,
				null,
				[ 700, 0.01, 0.01, 0, 0 ],
				[ 1, 0.05, 0.05, 0, 0 ],
				[ 1, 0, 0.0031, 0, 0 ],
				null,
				null
			],
			"immobilizedBy": [ "Large Bear Trap" ],
			"breeding": {
				"gestationTime": 0,
				"incubationTime": 8999.28006,
				"eggTempMin": 24,
				"eggTempMax": 28,
				"maturationTime": 878348.704,
				"matingCooldownMin": 64800,
				"matingCooldownMax": 172800
			},
			"colors": [
				{
					"name": "Body Main",
					"colors": [
						"Black",
						"Dark Green",
						"Dark Grey",
						"Dino Albino",
						"Dino Dark Green",
						"Dino Dark Red",
						"Dino Darker Grey",
						"Dino Ligh Red",
						"Dino Light Green",
						"Dino Medium Green",
						"DragonGreen2",
						"Light Green",
						"Light Grey",
						"Light Red",
						"NearWhite",
						"Red"
					]
				},
				{
					"name": "UnderBelly",
					"colors": [
						"Black",
						"Dark Green",
						"Dark Grey",
						"Dino Albino",
						"Dino Dark Green",
						"Dino Dark Red",
						"Dino Darker Grey",
						"Dino Ligh Red",
						"Dino Light Green",
						"Dino Medium Green",
						"DragonGreen2",
						"Light Green",
						"Light Grey",
						"Light Red",
						"NearWhite",
						"Red"
					]
				},
				{
					"name": "Main Highlights",
					"colors": [
						"Black",
						"Dark Green",
						"Dark Grey",
						"Dino Albino",
						"Dino Dark Green",
						"Dino Dark Red",
						"Dino Darker Grey",
						"Dino Ligh Red",
						"Dino Light Green",
						"Dino Medium Green",
						"DragonGreen2",
						"Light Green",
						"Light Grey",
						"Light Red",
						"NearWhite",
						"Red"
					]
				},
				{
					"name": "Highlights",
					"colors": [
						"Black",
						"Dark Green",
						"Dark Grey",
						"Dino Albino",
						"Dino Dark Green",
						"Dino Dark Red",
						"Dino Darker Grey",
						"Dino Ligh Red",
						"Dino Light Green",
						"Dino Medium Green",
						"DragonGreen2",
						"Light Green",
						"Light Grey",
						"Light Red",
						"NearWhite",
						"Red"
					]
				},
				{
					"name": "Head Main",
					"colors": [
						"Black",
						"Dark Green",
						"Dark Grey",
						"Dino Albino",
						"Dino Dark Green",
						"Dino Dark Red",
						"Dino Darker Grey",
						"Dino Ligh Red",
						"Dino Light Green",
						"Dino Medium Green",
						"DragonGreen2",
						"Light Green",
						"Light Grey",
						"Light Red",
						"NearWhite",
						"Red"
					]
				},
				{
					"name": "Emissive",
					"colors": [
						"Dino Albino",
						"Dino Light Blue",
						"Dino Light Purple",
						"Light Green",
						"Light Orange",
						"Light Red",
						"Light Yellow"
					]
				}
			],
			"taming": {
				"nonViolent": false,
				"violent": true,
				"tamingIneffectiveness": 1.25,
				"affinityNeeded0": 5000,
				"affinityIncreasePL": 160,
				"torporDepletionPS0": 120,
				"foodConsumptionBase": 0.002314,
				"foodConsumptionMult": 160.0563,
				"babyFoodConsumptionMult": 900,
				"adultFoodConsumptionMult": 3
			},
			"TamedBaseHealthMultiplier": 1,
			"displayedStats": 927
		},
		{
			"name": "Skeletal Giganotosaurus",
			"blueprintPath": "/Game/Mods/GigaFullTame/Bone_GigantFullTame_Character_BP.Bone_GigantFullTame_Character_BP",
			"fullStatsRaw": [
				[ 80000, 0.0005, 0.002, 0, 0 ],
				[ 400, 0.0005, 0.01, 0, 0 ],
				[ 10000, 0.06, 0, 0, 0 ],
				[ 150, 0.0025, 0.025, 0, 0 ],
				[ 4000, 0.0025, 0.025, 0, 0 ],
				null,
				null,
				[ 700, 0.01, 0.01, 0, 0 ],
				[ 1, 0.05, 0.05, 0, 0 ],
				[ 1, 0, 0.0031, 0, 0 ],
				null,
				null
			],
			"immobilizedBy": [ "Large Bear Trap" ],
			"breeding": {
				"gestationTime": 0,
				"incubationTime": 179985.601,
				"eggTempMin": 43,
				"eggTempMax": 44,
				"maturationTime": 878348.704,
				"matingCooldownMin": 64800,
				"matingCooldownMax": 172800
			},
			"colors": [
				{
					"name": "Unknown",
					"colors": [
						"Black",
						"Dark Grey",
						"Dino Dark Brown",
						"Dino Dark Green",
						"Dino Dark Red",
						"Dino Dark Yellow",
						"Dino Darker Grey",
						"Dino Light Brown",
						"Dino Light Green",
						"Dino Light Yellow",
						"Dino Medium Brown",
						"Dino Medium Green",
						"Light Grey"
					]
				},
				null,
				null,
				null,
				{
					"name": "Unknown",
					"colors": [
						"Black",
						"Dino Dark Red",
						"Dino Light Brown",
						"Dino Light Green",
						"Dino Light Yellow",
						"Dino Medium Brown",
						"Dino Medium Green",
						"Light Grey"
					]
				},
				{
					"name": "Unknown",
					"colors": [
						"Black",
						"Dark Grey",
						"Dino Dark Brown",
						"Dino Dark Green",
						"Dino Dark Red",
						"Dino Darker Grey",
						"Dino Medium Brown",
						"Dino Medium Green"
					]
				}
			],
			"taming": {
				"nonViolent": false,
				"violent": false,
				"tamingIneffectiveness": 1.25,
				"affinityNeeded0": 5000,
				"affinityIncreasePL": 160,
				"foodConsumptionBase": 0.002314,
				"foodConsumptionMult": 160.0563,
				"babyFoodConsumptionMult": 900,
				"adultFoodConsumptionMult": 3
			},
			"TamedBaseHealthMultiplier": 1,
			"displayedStats": 927
		},
		{
			"name": "Giganotosaurus",
			"blueprintPath": "/Game/Mods/GigaFullTame/GigantFullTame_Character_BP.GigantFullTame_Character_BP",
			"fullStatsRaw": [
				[ 80000, 0.0005, 0.002, 0, 0 ],
				[ 400, 0.0005, 0.01, 0, 0 ],
				[ 10000, 0.06, 0, 0, 0 ],
				[ 150, 0.0025, 0.025, 0, 0 ],
				[ 4000, 0.0025, 0.025, 0, 0 ],
				null,
				null,
				[ 700, 0.01, 0.01, 0, 0 ],
				[ 1, 0.05, 0.05, 0, 0 ],
				[ 1, 0, 0.0031, 0, 0 ],
				null,
				null
			],
			"immobilizedBy": [ "Large Bear Trap" ],
			"breeding": {
				"gestationTime": 0,
				"incubationTime": 179985.601,
				"eggTempMin": 43,
				"eggTempMax": 44,
				"maturationTime": 878348.704,
				"matingCooldownMin": 64800,
				"matingCooldownMax": 172800
			},
			"colors": [
				{
					"name": "Unknown",
					"colors": [
						"Black",
						"Dark Grey",
						"Dino Dark Brown",
						"Dino Dark Green",
						"Dino Dark Red",
						"Dino Dark Yellow",
						"Dino Darker Grey",
						"Dino Light Brown",
						"Dino Light Green",
						"Dino Light Yellow",
						"Dino Medium Brown",
						"Dino Medium Green",
						"Light Grey"
					]
				},
				null,
				null,
				null,
				{
					"name": "Unknown",
					"colors": [
						"Black",
						"Dino Dark Red",
						"Dino Light Brown",
						"Dino Light Green",
						"Dino Light Yellow",
						"Dino Medium Brown",
						"Dino Medium Green",
						"Light Grey"
					]
				},
				{
					"name": "Unknown",
					"colors": [
						"Black",
						"Dark Grey",
						"Dino Dark Brown",
						"Dino Dark Green",
						"Dino Dark Red",
						"Dino Darker Grey",
						"Dino Medium Brown",
						"Dino Medium Green"
					]
				}
			],
			"taming": {
				"nonViolent": false,
				"violent": true,
				"tamingIneffectiveness": 1.25,
				"affinityNeeded0": 5000,
				"affinityIncreasePL": 160,
				"torporDepletionPS0": 120,
				"foodConsumptionBase": 0.002314,
				"foodConsumptionMult": 160.0563,
				"babyFoodConsumptionMult": 900,
				"adultFoodConsumptionMult": 3
			},
			"TamedBaseHealthMultiplier": 1,
			"displayedStats": 927
		},
		{
			"name": "Skeletal Giganotosaurus",
			"blueprintPath": "/Game/Mods/GigaFullTame/PrimalEarth/Dinos/Giganotosaurus/Bone_Gigant_Character_BP.Bone_Gigant_Character_BP",
			"fullStatsRaw": [
				[ 80000, 0.0005, 0.002, -63000, 0 ],
				[ 400, 0.0005, 0.01, 0, 0 ],
				[ 10000, 0.06, 0, 0, 0 ],
				[ 150, 0.0025, 0.025, 0, 0 ],
				[ 4000, 0.0025, 0.025, 0, 0 ],
				null,
				null,
				[ 700, 0.01, 0.01, 0, 0 ],
				[ 1, 0.05, 0.05, -0.8, 0 ],
				[ 1, 0, 0.0031, 0, 0 ],
				null,
				null
			],
			"immobilizedBy": [ "Large Bear Trap" ],
			"breeding": {
				"gestationTime": 0,
				"incubationTime": 179985.601,
				"eggTempMin": 43,
				"eggTempMax": 44,
				"maturationTime": 878348.704,
				"matingCooldownMin": 64800,
				"matingCooldownMax": 172800
			},
			"colors": [
				{
					"name": "Unknown",
					"colors": [
						"Black",
						"Dark Grey",
						"Dino Dark Brown",
						"Dino Dark Green",
						"Dino Dark Red",
						"Dino Dark Yellow",
						"Dino Darker Grey",
						"Dino Light Brown",
						"Dino Light Green",
						"Dino Light Yellow",
						"Dino Medium Brown",
						"Dino Medium Green",
						"Light Grey"
					]
				},
				null,
				null,
				null,
				{
					"name": "Unknown",
					"colors": [
						"Black",
						"Dino Dark Red",
						"Dino Light Brown",
						"Dino Light Green",
						"Dino Light Yellow",
						"Dino Medium Brown",
						"Dino Medium Green",
						"Light Grey"
					]
				},
				{
					"name": "Unknown",
					"colors": [
						"Black",
						"Dark Grey",
						"Dino Dark Brown",
						"Dino Dark Green",
						"Dino Dark Red",
						"Dino Darker Grey",
						"Dino Medium Brown",
						"Dino Medium Green"
					]
				}
			],
			"taming": {
				"nonViolent": false,
				"violent": false,
				"tamingIneffectiveness": 1.25,
				"affinityNeeded0": 5000,
				"affinityIncreasePL": 160,
				"foodConsumptionBase": 0.002314,
				"foodConsumptionMult": 160.0563,
				"babyFoodConsumptionMult": 900,
				"adultFoodConsumptionMult": 3
			},
			"TamedBaseHealthMultiplier": 1,
			"displayedStats": 927
		},
		{
			"name": "Corrupted Dinotar",
			"blueprintPath": "/Game/Mods/GigaFullTame/VRGigantFullTame_Character_BP.VRGigantFullTame_Character_BP",
			"fullStatsRaw": [
				[ 80000, 0.0005, 0.002, 0, 0 ],
				[ 400, 0.0005, 0.01, 0, 0 ],
				[ 10000, 0.06, 0, 0, 0 ],
				[ 150, 0.0025, 0.025, 0, 0 ],
				[ 4000, 0.0025, 0.025, 0, 0 ],
				null,
				null,
				[ 700, 0.01, 0.01, 0, 0 ],
				[ 1, 0.05, 0.05, 0, 0 ],
				[ 1, 0, 0.0031, 0, 0 ],
				null,
				null
			],
			"immobilizedBy": [ "Large Bear Trap" ],
			"breeding": {
				"gestationTime": 0,
				"incubationTime": 179985.601,
				"eggTempMin": 43,
				"eggTempMax": 44,
				"maturationTime": 878348.704,
				"matingCooldownMin": 64800,
				"matingCooldownMax": 172800
			},
			"taming": {
				"nonViolent": false,
				"violent": true,
				"tamingIneffectiveness": 1.25,
				"affinityNeeded0": 5000,
				"affinityIncreasePL": 160,
				"torporDepletionPS0": 120,
				"foodConsumptionBase": 0.002314,
				"foodConsumptionMult": 160.0563,
				"babyFoodConsumptionMult": 900,
				"adultFoodConsumptionMult": 3
			},
			"TamedBaseHealthMultiplier": 1,
			"displayedStats": 927
		}
	]
}