{
	"version": "306.41.1582543058",
	"format": "1",
	"mod": {
		"id": "1083349027",
		"tag": "SpeedyFlyers",
		"title": "Najs Speedy Flyers"
	},
	"species": [
		{
			"name": "Ice Wyvern",
			"blueprintPath": "/Game/Mods/SpeedyFlyers/Assets/Dinos/IceWyvern/Ragnarok_Wyvern_Override_Ice.Ragnarok_Wyvern_Override_Ice_C",
			"dinoNameTag": "Wyvern",
			"customTag": "Wyvern",
			"targetingTeamName": "Carnivores_High",
			"mass": 800,
			"dragWeight": 555,
			"flags": [
				"allowFlyerLandedRider",
				"allowRiding",
				"canBeDragged",
				"canBeTorpid",
				"canDrag",
				"doStepDamage",
				"isBigDino",
				"isCarnivore",
				"isFlyerDino"
			],
			"falling": {
				"dmgMult": 80,
				"maxSpeed": 1550
			},
			"movementW": {
				"walk": { "base": 345, "sprint": 796.9 },
				"fly": { "base": 1500, "sprint": 1000 },
				"swim": { "base": 550 }
			},
			"movementD": {
				"walk": { "base": 345, "sprint": 796.9 },
				"fly": { "base": 1500, "sprint": 1000 },
				"swim": { "base": 550 }
			},
			"attack": {
				"defaultDmg": 160,
				"defaultSwingRadius": 1200,
				"attacks": [
					{ "name": "Bite", "interval": 0.5, "dmg": 80, "radius": 495, "stamina": 10 },
					{ "name": "Flame", "interval": 5, "dmg": 0, "radius": 0, "stamina": 160 },
					{ "name": "Grab", "interval": 1, "dmg": 18, "radius": 300, "stamina": 40 },
					{ "name": "Taunt", "interval": 0, "dmg": 60, "radius": 2000, "stamina": 2 },
					{ "name": "Bite (AI)", "interval": 0.5, "dmg": 80, "radius": 614, "stamina": 10 }
				]
			}
		},
		{
			"name": "Ice Wyvern",
			"blueprintPath": "/Game/Mods/SpeedyFlyers/Custom_Assets/Dinos/Wyvern/Ice_Wyvern/Ragnarok_Wyvern_Override_Ice.Ragnarok_Wyvern_Override_Ice_C",
			"dinoNameTag": "Wyvern",
			"customTag": "Wyvern",
			"targetingTeamName": "Carnivores_High",
			"mass": 800,
			"dragWeight": 555,
			"flags": [
				"allowFlyerLandedRider",
				"allowRiding",
				"canBeDragged",
				"canBeTorpid",
				"canDrag",
				"doStepDamage",
				"isBigDino",
				"isCarnivore",
				"isFlyerDino"
			],
			"falling": {
				"dmgMult": 80,
				"maxSpeed": 1550
			},
			"movementW": {
				"walk": { "base": 345, "sprint": 796.9 },
				"fly": { "base": 1500, "sprint": 1000 },
				"swim": { "base": 550 }
			},
			"movementD": {
				"walk": { "base": 345, "sprint": 796.9 },
				"fly": { "base": 1500, "sprint": 1000 },
				"swim": { "base": 550 }
			},
			"attack": {
				"defaultDmg": 160,
				"defaultSwingRadius": 1200,
				"attacks": [
					{ "name": "Bite", "interval": 0.5, "dmg": 80, "radius": 495, "stamina": 10 },
					{ "name": "Flame", "interval": 5, "dmg": 0, "radius": 0, "stamina": 160 },
					{ "name": "Grab", "interval": 1, "dmg": 18, "radius": 300, "stamina": 40 },
					{ "name": "Taunt", "interval": 0, "dmg": 60, "radius": 2000, "stamina": 2 },
					{ "name": "Bite (AI)", "interval": 0.5, "dmg": 80, "radius": 614, "stamina": 10 }
				]
			}
		},
		{
			"name": "PrimalCharacter",
			"blueprintPath": "/Game/Mods/SpeedyFlyers/Custom_Assets/Dinos/Wyvern/Ragnarok_Wyvern_Override.Ragnarok_Wyvern_Override_C",
			"dinoNameTag": "Wyvern",
			"customTag": "Wyvern",
			"targetingTeamName": "Carnivores_High",
			"mass": 800,
			"dragWeight": 555,
			"flags": [
				"allowFlyerLandedRider",
				"allowRiding",
				"canBeDragged",
				"canBeTorpid",
				"canDrag",
				"doStepDamage",
				"isBigDino",
				"isCarnivore",
				"isFlyerDino"
			],
			"falling": {
				"dmgMult": 80,
				"maxSpeed": 1550
			},
			"movementW": {
				"walk": { "base": 345, "sprint": 796.9 },
				"fly": { "base": 1500, "sprint": 1000 },
				"swim": { "base": 550 }
			},
			"movementD": {
				"walk": { "base": 345, "sprint": 796.9 },
				"fly": { "base": 1500, "sprint": 1000 },
				"swim": { "base": 550 }
			},
			"attack": {
				"defaultDmg": 160,
				"defaultSwingRadius": 1200,
				"attacks": [
					{ "name": "Bite", "interval": 0.5, "dmg": 80, "radius": 495, "stamina": 10 },
					{ "name": "Flame", "interval": 5, "dmg": 0, "radius": 0, "stamina": 160 },
					{ "name": "Grab", "interval": 1, "dmg": 18, "radius": 300, "stamina": 40 },
					{ "name": "Taunt", "interval": 0, "dmg": 60, "radius": 2000, "stamina": 2 },
					{ "name": "Bite (AI)", "interval": 0.5, "dmg": 80, "radius": 614, "stamina": 10 }
				]
			}
		},
		{
			"name": "Argentavis",
			"blueprintPath": "/Game/Mods/SpeedyFlyers/Dinos/Argentavis/Argent_Character_BP.Argent_Character_BP_C",
			"dinoNameTag": "Argent",
			"customTag": "Argent",
			"targetingTeamName": "Carnivores_Medium_TargetPlayerOrTamed",
			"mass": 190,
			"dragWeight": 150,
			"flags": [
				"allowFlyerLandedRider",
				"allowRiding",
				"canBeDragged",
				"canBeTorpid",
				"canDrag",
				"isFlyerDino"
			],
			"falling": {
				"dmgMult": 80,
				"maxSpeed": 1550
			},
			"movementW": {
				"walk": { "base": 140.1, "sprint": 315.3 },
				"fly": { "base": 323.3 },
				"swim": { "base": 161.7 }
			},
			"movementD": {
				"walk": { "base": 260, "sprint": 585 },
				"fly": { "base": 600 },
				"swim": { "base": 300 }
			},
			"attack": {
				"defaultDmg": 25,
				"defaultSwingRadius": 210,
				"attacks": [
					{ "name": "None", "interval": 0.6, "dmg": 25, "radius": 240, "stamina": 0 },
					{ "name": "GrabClaws", "interval": 4, "dmg": 12, "radius": 400, "stamina": 120 },
					{ "name": "GrabBeak", "interval": 4, "dmg": 12, "radius": 300, "stamina": 120 }
				]
			}
		},
		{
			"name": "Corrupted Pteranodon",
			"blueprintPath": "/Game/Mods/SpeedyFlyers/Dinos/Corrupt/Ptero/Ptero_Character_BP_Corrupt.Ptero_Character_BP_Corrupt_C",
			"dinoNameTag": "Ptera Corrupt",
			"customTag": "Ptera",
			"targetingTeamName": "Carnivores_High",
			"mass": 190,
			"dragWeight": 149,
			"variants": [ "Corrupted" ],
			"flags": [
				"allowFlyerLandedRider",
				"allowRiding",
				"canBeDragged",
				"canBeTorpid",
				"canDrag",
				"isCarnivore",
				"isCorrupted",
				"isFlyerDino"
			],
			"falling": {
				"dmgMult": 80,
				"maxSpeed": 1550
			},
			"movementW": {
				"walk": { "base": 226.1, "sprint": 715 },
				"fly": { "base": 521.7 },
				"swim": { "base": 260.9 }
			},
			"movementD": {
				"walk": { "base": 260, "sprint": 822.2 },
				"fly": { "base": 600 },
				"swim": { "base": 300 }
			},
			"attack": {
				"defaultDmg": 15,
				"defaultSwingRadius": 200,
				"attacks": [
					{ "name": "None", "interval": 0.6, "dmg": 12, "radius": 200, "stamina": 0 },
					{ "name": "None", "interval": 1, "dmg": 18, "radius": 200, "stamina": 40 },
					{ "name": "Barrel Roll", "interval": 0.6, "dmg": 50, "radius": 260, "stamina": 90 }
				]
			}
		},
		{
			"name": "Corrupted Rock Drake",
			"blueprintPath": "/Game/Mods/SpeedyFlyers/Dinos/Corrupt/RockDrake/RockDrake_Character_BP_Corrupt.RockDrake_Character_BP_Corrupt_C",
			"dinoNameTag": "RockDrake Corrupt",
			"customTag": "RockDrake",
			"targetingTeamName": "Carnivores_High",
			"mass": 345,
			"dragWeight": 425,
			"variants": [ "Corrupted" ],
			"flags": [
				"allowMountedWeaponry",
				"allowRiding",
				"canBeDragged",
				"canBeTorpid",
				"doStepDamage",
				"isCarnivore",
				"isCorrupted"
			],
			"falling": {
				"dmgMult": 10,
				"maxSpeed": 1550
			},
			"movementW": {
				"walk": { "base": 520, "sprint": 1820 },
				"swim": { "base": 480 }
			},
			"movementD": {
				"walk": { "base": 585, "sprint": 2047.5 },
				"swim": { "base": 540 }
			},
			"attack": {
				"defaultDmg": 0,
				"defaultSwingRadius": 600,
				"attacks": [
					{ "name": "Bite", "interval": 0.5, "dmg": 60, "radius": 600, "stamina": 20 },
					{ "name": "Toggle Climbing", "interval": 0, "dmg": 0, "radius": 0, "stamina": 0 },
					{ "name": "Toggle Camo", "interval": 0, "dmg": 0, "radius": 0, "stamina": 0 },
					{ "name": "Pounce_DirectHit", "interval": 0, "dmg": 240, "radius": 0, "stamina": 0 },
					{ "name": "Pounce_AOE", "interval": 0, "dmg": 150, "radius": 0, "stamina": 0 },
					{ "name": "Bite (Climbing)", "interval": 0.5, "dmg": 60, "radius": 900, "stamina": 20 }
				]
			}
		},
		{
			"name": "Corrupted Wyvern",
			"blueprintPath": "/Game/Mods/SpeedyFlyers/Dinos/Corrupt/Wyvern/Wyvern_Character_BP_Fire_Corrupt.Wyvern_Character_BP_Fire_Corrupt_C",
			"dinoNameTag": "Wyvern",
			"customTag": "Wyvern",
			"targetingTeamName": "Carnivores_High",
			"mass": 800,
			"dragWeight": 555,
			"variants": [ "Corrupted" ],
			"flags": [
				"allowFlyerLandedRider",
				"allowRiding",
				"canBeDragged",
				"canBeTorpid",
				"canDrag",
				"doStepDamage",
				"isBigDino",
				"isCarnivore",
				"isCorrupted",
				"isFlyerDino"
			],
			"falling": {
				"dmgMult": 80,
				"maxSpeed": 1550
			},
			"movementW": {
				"walk": { "base": 345, "sprint": 796.9 },
				"fly": { "base": 1500, "sprint": 1000 },
				"swim": { "base": 550 }
			},
			"movementD": {
				"walk": { "base": 345, "sprint": 796.9 },
				"fly": { "base": 1500, "sprint": 1000 },
				"swim": { "base": 550 }
			},
			"attack": {
				"defaultDmg": 160,
				"defaultSwingRadius": 1200,
				"attacks": [
					{ "name": "Bite", "interval": 0.5, "dmg": 80, "radius": 495, "stamina": 10 },
					{ "name": "Flame", "interval": 5, "dmg": 0, "radius": 0, "stamina": 160 },
					{ "name": "Grab", "interval": 1, "dmg": 18, "radius": 300, "stamina": 40 },
					{ "name": "Taunt", "interval": 0, "dmg": 60, "radius": 2000, "stamina": 2 },
					{ "name": "Bite (AI)", "interval": 0.5, "dmg": 80, "radius": 614, "stamina": 10 }
				]
			}
		},
		{
			"name": "Griffin",
			"blueprintPath": "/Game/Mods/SpeedyFlyers/Dinos/Griffin/Griffin_Character_BP.Griffin_Character_BP_C",
			"dinoNameTag": "Griffin",
			"customTag": "Griffin",
			"targetingTeamName": "Carnivores_Medium_Aggressive",
			"mass": 190,
			"dragWeight": 200,
			"flags": [
				"allowFlyerLandedRider",
				"allowMountedWeaponry",
				"allowRiding",
				"canBeDragged",
				"canBeTorpid",
				"canDrag",
				"isBigDino",
				"isCarnivore",
				"isFlyerDino"
			],
			"falling": {
				"dmgMult": 80,
				"maxSpeed": 1550
			},
			"movementW": {
				"walk": { "base": 300, "sprint": 750 },
				"fly": { "base": 750, "sprint": 600 },
				"swim": { "base": 300 }
			},
			"movementD": {
				"walk": { "base": 300, "sprint": 750 },
				"fly": { "base": 750, "sprint": 600 },
				"swim": { "base": 300 }
			},
			"attack": {
				"defaultDmg": 18,
				"defaultSwingRadius": 400,
				"attacks": [
					{ "name": "Claw", "interval": 2, "dmg": 27, "radius": 700, "stamina": 0 },
					{ "name": "Grab", "interval": 1, "dmg": 12, "radius": 500, "stamina": 60 },
					{ "name": "DivingSwipe", "interval": 3, "dmg": 188, "radius": 1500, "stamina": 25 },
					{ "name": "DiveBomb", "interval": 2, "dmg": 115, "radius": 2000, "stamina": 30 }
				]
			}
		},
		{
			"name": "Managarmr",
			"blueprintPath": "/Game/Mods/SpeedyFlyers/Dinos/IceJumper/IceJumper_Character_BP.IceJumper_Character_BP_C",
			"dinoNameTag": "Managarmr",
			"customTag": "Managarmr",
			"targetingTeamName": "Carnivores_Medium",
			"mass": 222,
			"dragWeight": 250,
			"flags": [
				"allowRiding",
				"canBeDragged",
				"canBeTorpid",
				"canDrag",
				"isCarnivore"
			],
			"falling": {
				"dmgMult": 40,
				"maxSpeed": 1550
			},
			"movementW": {
				"walk": { "base": 1250, "sprint": 2500 },
				"swim": { "base": 1050 }
			},
			"movementD": {
				"walk": { "base": 1250, "sprint": 2500 },
				"swim": { "base": 1050 }
			},
			"attack": {
				"defaultDmg": 42,
				"defaultSwingRadius": 300,
				"attacks": [
					{ "name": "DashFwd", "interval": 1, "dmg": 10, "radius": 0, "stamina": 0 },
					{
						"name": "IceBreath", "interval": 10, "dmg": 15, "radius": 0, "stamina": 15,
						"isProjectile": true
					},
					{ "name": "Bite", "interval": 1, "dmg": 35, "radius": 300, "stamina": 0 }
				]
			}
		},
		{
			"name": "Lymantria",
			"blueprintPath": "/Game/Mods/SpeedyFlyers/Dinos/Moth/Moth_Character_BP.Moth_Character_BP_C",
			"dinoNameTag": "Moth",
			"customTag": "Moth",
			"targetingTeamName": "Herbivores",
			"mass": 190,
			"dragWeight": 149,
			"flags": [
				"allowFlyerLandedRider",
				"allowRiding",
				"canBeDragged",
				"canBeTorpid",
				"canDrag",
				"isFlyerDino"
			],
			"falling": {
				"dmgMult": 80,
				"maxSpeed": 1550
			},
			"movementW": {
				"walk": { "base": 110, "sprint": 220 },
				"fly": { "base": 600 },
				"swim": { "base": 300 }
			},
			"movementD": {
				"walk": { "base": 96.8, "sprint": 193.6 },
				"fly": { "base": 528 },
				"swim": { "base": 264 }
			},
			"attack": {
				"defaultDmg": 15,
				"defaultSwingRadius": 200,
				"attacks": [ { "name": "DropSpores", "interval": 17, "dmg": 18, "radius": 200, "stamina": 50 } ]
			}
		},
		{
			"name": "Snow Owl",
			"blueprintPath": "/Game/Mods/SpeedyFlyers/Dinos/Owl/Owl_Character_BP.Owl_Character_BP_C",
			"dinoNameTag": "Owl",
			"customTag": "Owl",
			"targetingTeamName": "",
			"mass": 250,
			"dragWeight": 250,
			"flags": [
				"allowFlyerLandedRider",
				"allowRiding",
				"canBeDragged",
				"canBeTorpid",
				"isFlyerDino",
				"preventCharacterBasing"
			],
			"falling": {
				"dmgMult": 80,
				"maxSpeed": 1550
			},
			"movementW": {
				"walk": { "base": 260, "sprint": 728 },
				"fly": { "base": 600 },
				"swim": { "base": 300 }
			},
			"movementD": {
				"walk": { "base": 260, "sprint": 728 },
				"fly": { "base": 600 },
				"swim": { "base": 300 }
			},
			"attack": {
				"defaultDmg": 15,
				"defaultSwingRadius": 90,
				"attacks": [
					{ "name": "Melee", "interval": 0.6, "dmg": 25, "radius": 240, "stamina": 0 },
					{ "name": "Encapsulate", "interval": 0, "dmg": 0, "radius": 0, "stamina": 0 },
					{ "name": "PredatorVision", "interval": 0, "dmg": 0, "radius": 0, "stamina": 0 }
				]
			}
		},
		{
			"name": "Pelagornis",
			"blueprintPath": "/Game/Mods/SpeedyFlyers/Dinos/Pelagornis/Pela_Character_BP.Pela_Character_BP_C",
			"dinoNameTag": "Pela",
			"customTag": "Pela",
			"targetingTeamName": "Herbivores",
			"mass": 190,
			"dragWeight": 120,
			"flags": [
				"allowFlyerLandedRider",
				"allowRiding",
				"canBeDragged",
				"canBeTorpid",
				"canDrag",
				"isFlyerDino"
			],
			"falling": {
				"dmgMult": 80,
				"maxSpeed": 1550
			},
			"movementW": {
				"walk": { "base": 114.8, "sprint": 229.6 },
				"fly": { "base": 521.7 },
				"swim": { "base": 287 }
			},
			"movementD": {
				"walk": { "base": 132, "sprint": 264 },
				"fly": { "base": 600 },
				"swim": { "base": 330 }
			},
			"attack": {
				"defaultDmg": 16,
				"defaultSwingRadius": 170,
				"attacks": [ { "name": "None", "interval": 0.6, "dmg": 16, "radius": 170, "stamina": 0 } ]
			}
		},
		{
			"name": "Phoenix",
			"blueprintPath": "/Game/Mods/SpeedyFlyers/Dinos/Phoenix/Phoenix_Character_BP.Phoenix_Character_BP_C",
			"dinoNameTag": "Phoenix",
			"customTag": "Phoenix",
			"targetingTeamName": "Herbivores",
			"mass": 190,
			"dragWeight": 35,
			"flags": [
				"allowRiding",
				"canBeDragged",
				"canDrag",
				"isCarnivore",
				"isFlyerDino"
			],
			"falling": {
				"dmgMult": 80,
				"maxSpeed": 1550
			},
			"movementW": {
				"walk": { "base": 364, "sprint": 637 },
				"fly": { "base": 840 },
				"swim": { "base": 420 }
			},
			"movementD": {
				"walk": { "base": 520, "sprint": 910 },
				"fly": { "base": 1200 },
				"swim": { "base": 600 }
			},
			"attack": {
				"defaultDmg": 14,
				"defaultSwingRadius": 185,
				"attacks": [
					{ "name": "Attack Bite", "interval": 0.6, "dmg": 14, "radius": 350, "stamina": 0 },
					{
						"name": "Fireball (Rider)", "interval": 4, "dmg": 0, "radius": 0, "stamina": 75,
						"isProjectile": true
					},
					{ "name": "Melee Rake", "interval": 1, "dmg": 23, "radius": 350, "stamina": 0 }
				]
			}
		},
		{
			"name": "Pteranodon",
			"blueprintPath": "/Game/Mods/SpeedyFlyers/Dinos/Ptero/Ptero_Character_BP.Ptero_Character_BP_C",
			"dinoNameTag": "Ptera",
			"customTag": "Ptera",
			"targetingTeamName": "Herbivores",
			"mass": 190,
			"dragWeight": 149,
			"flags": [
				"allowFlyerLandedRider",
				"allowRiding",
				"canBeDragged",
				"canBeTorpid",
				"canDrag",
				"isFlyerDino"
			],
			"falling": {
				"dmgMult": 80,
				"maxSpeed": 1550
			},
			"movementW": {
				"walk": { "base": 226.1, "sprint": 715 },
				"fly": { "base": 521.7 },
				"swim": { "base": 260.9 }
			},
			"movementD": {
				"walk": { "base": 260, "sprint": 822.2 },
				"fly": { "base": 600 },
				"swim": { "base": 300 }
			},
			"attack": {
				"defaultDmg": 15,
				"defaultSwingRadius": 200,
				"attacks": [
					{ "name": "None", "interval": 0.6, "dmg": 18, "radius": 200, "stamina": 0 },
					{ "name": "None", "interval": 1, "dmg": 18, "radius": 200, "stamina": 40 },
					{ "name": "Barrel Roll", "interval": 0.6, "dmg": 50, "radius": 260, "stamina": 90 }
				]
			}
		},
		{
			"name": "Tek Quetzal",
			"blueprintPath": "/Game/Mods/SpeedyFlyers/Dinos/Quetzalcoatlus/BionicQuetz_Character_BP.BionicQuetz_Character_BP_C",
			"dinoNameTag": "Quetz",
			"customTag": "Quetz",
			"targetingTeamName": "Herbivores",
			"mass": 190,
			"dragWeight": 500,
			"flags": [
				"allowFlyerLandedRider",
				"allowRiding",
				"canBeDragged",
				"canBeTorpid",
				"canDrag",
				"isBigDino",
				"isFlyerDino"
			],
			"falling": {
				"dmgMult": 80,
				"maxSpeed": 1550
			},
			"movementW": {
				"walk": { "base": 574.6, "sprint": 1149.1 },
				"fly": { "base": 798 },
				"swim": { "base": 478.8 }
			},
			"movementD": {
				"walk": { "base": 342, "sprint": 684 },
				"fly": { "base": 475 },
				"swim": { "base": 285 }
			},
			"attack": {
				"defaultDmg": 32,
				"defaultSwingRadius": 200,
				"attacks": [
					{ "name": "None", "interval": 0.6, "dmg": 32, "radius": 720, "stamina": 16 },
					{ "name": "None", "interval": 1, "dmg": 32, "radius": 370, "stamina": 80 }
				]
			}
		},
		{
			"name": "Quetzal",
			"blueprintPath": "/Game/Mods/SpeedyFlyers/Dinos/Quetzalcoatlus/Quetz_Character_BP.Quetz_Character_BP_C",
			"dinoNameTag": "Quetz",
			"customTag": "Quetz",
			"targetingTeamName": "Herbivores",
			"mass": 190,
			"dragWeight": 500,
			"flags": [
				"allowFlyerLandedRider",
				"allowRiding",
				"canBeDragged",
				"canBeTorpid",
				"canDrag",
				"isBigDino",
				"isFlyerDino"
			],
			"falling": {
				"dmgMult": 80,
				"maxSpeed": 1550
			},
			"movementW": {
				"walk": { "base": 574.6, "sprint": 1149.1 },
				"fly": { "base": 798 },
				"swim": { "base": 478.8 }
			},
			"movementD": {
				"walk": { "base": 342, "sprint": 684 },
				"fly": { "base": 475 },
				"swim": { "base": 285 }
			},
			"attack": {
				"defaultDmg": 32,
				"defaultSwingRadius": 200,
				"attacks": [
					{ "name": "None", "interval": 0.6, "dmg": 32, "radius": 720, "stamina": 16 },
					{ "name": "None", "interval": 1, "dmg": 32, "radius": 370, "stamina": 80 }
				]
			}
		},
		{
			"name": "Rock Drake",
			"blueprintPath": "/Game/Mods/SpeedyFlyers/Dinos/RockDrake/RockDrake_Character_BP.RockDrake_Character_BP_C",
			"dinoNameTag": "RockDrake",
			"customTag": "RockDrake",
			"targetingTeamName": "Carnivores_High",
			"mass": 345,
			"dragWeight": 425,
			"flags": [
				"allowMountedWeaponry",
				"allowRiding",
				"canBeDragged",
				"canBeTorpid",
				"doStepDamage",
				"isCarnivore"
			],
			"falling": {
				"dmgMult": 10,
				"maxSpeed": 1550
			},
			"movementW": {
				"walk": { "base": 520, "sprint": 1820 },
				"swim": { "base": 480 }
			},
			"movementD": {
				"walk": { "base": 585, "sprint": 2047.5 },
				"swim": { "base": 540 }
			},
			"attack": {
				"defaultDmg": 0,
				"defaultSwingRadius": 600,
				"attacks": [
					{ "name": "Bite", "interval": 0.5, "dmg": 60, "radius": 600, "stamina": 20 },
					{ "name": "Toggle Climbing", "interval": 0, "dmg": 0, "radius": 0, "stamina": 0 },
					{ "name": "Toggle Camo", "interval": 0, "dmg": 0, "radius": 0, "stamina": 0 },
					{ "name": "Pounce_DirectHit", "interval": 0, "dmg": 240, "radius": 0, "stamina": 0 },
					{ "name": "Pounce_AOE", "interval": 0, "dmg": 150, "radius": 0, "stamina": 0 },
					{ "name": "Bite (Climbing)", "interval": 0.5, "dmg": 60, "radius": 900, "stamina": 20 }
				]
			}
		},
		{
			"name": "Tapejara",
			"blueprintPath": "/Game/Mods/SpeedyFlyers/Dinos/Tapejara/Tapejara_Character_BP.Tapejara_Character_BP_C",
			"dinoNameTag": "Tapejara",
			"customTag": "Tapejara",
			"targetingTeamName": "Herbivores_Medium_Aggressive",
			"mass": 190,
			"dragWeight": 149,
			"flags": [
				"allowFlyerLandedRider",
				"allowRiding",
				"canBeDragged",
				"canBeTorpid",
				"canDrag",
				"isFlyerDino"
			],
			"falling": {
				"dmgMult": 80,
				"maxSpeed": 1550
			},
			"movementW": {
				"walk": { "base": 539, "sprint": 862.4 },
				"fly": { "base": 1540 },
				"swim": { "base": 660 }
			},
			"movementD": {
				"walk": { "base": 245, "sprint": 392 },
				"fly": { "base": 700 },
				"swim": { "base": 300 }
			},
			"attack": {
				"defaultDmg": 15,
				"defaultSwingRadius": 200,
				"attacks": [
					{ "name": "Bite", "interval": 0.6, "dmg": 18, "radius": 200, "stamina": 0 },
					{ "name": "Bite II", "interval": 1, "dmg": 18, "radius": 200, "stamina": 40 },
					{ "name": "Taunt", "interval": 0.6, "dmg": 18, "radius": 200, "stamina": 0 }
				]
			}
		},
		{
			"name": "Alpha Fire Wyvern",
			"blueprintPath": "/Game/Mods/SpeedyFlyers/Dinos/Wyvern/MegaWyvern_Character_BP_Fire.MegaWyvern_Character_BP_Fire_C",
			"dinoNameTag": "Wyvern",
			"customTag": "Wyvern",
			"targetingTeamName": "Carnivores_High",
			"mass": 800,
			"dragWeight": 555,
			"flags": [
				"allowFlyerLandedRider",
				"allowRiding",
				"canBeDragged",
				"canBeTorpid",
				"canDrag",
				"doStepDamage",
				"isBigDino",
				"isCarnivore",
				"isFlyerDino"
			],
			"falling": {
				"dmgMult": 80,
				"maxSpeed": 1550
			},
			"movementW": {
				"walk": { "base": 345, "sprint": 796.9 },
				"fly": { "base": 1500, "sprint": 1000 },
				"swim": { "base": 550 }
			},
			"movementD": {
				"walk": { "base": 345, "sprint": 796.9 },
				"fly": { "base": 1500, "sprint": 1000 },
				"swim": { "base": 550 }
			},
			"attack": {
				"defaultDmg": 210,
				"defaultSwingRadius": 1200,
				"attacks": [
					{ "name": "Bite", "interval": 0.5, "dmg": 140, "radius": 495, "stamina": 10 },
					{ "name": "Flame", "interval": 5, "dmg": 0, "radius": 0, "stamina": 20 },
					{ "name": "Grab", "interval": 1, "dmg": 18, "radius": 300, "stamina": 40 },
					{ "name": "Taunt", "interval": 0, "dmg": 90, "radius": 2000, "stamina": 2 },
					{ "name": "Bite (AI)", "interval": 0.5, "dmg": 120, "radius": 614, "stamina": 10 }
				]
			}
		},
		{
			"name": "Wyvern",
			"blueprintPath": "/Game/Mods/SpeedyFlyers/Dinos/Wyvern/Wyvern_Character_BP_Base.Wyvern_Character_BP_Base_C",
			"dinoNameTag": "Wyvern",
			"customTag": "Wyvern",
			"targetingTeamName": "Carnivores_High",
			"mass": 800,
			"dragWeight": 555,
			"flags": [
				"allowFlyerLandedRider",
				"allowRiding",
				"canBeDragged",
				"canBeTorpid",
				"canDrag",
				"doStepDamage",
				"isBigDino",
				"isCarnivore",
				"isFlyerDino"
			],
			"falling": {
				"dmgMult": 80,
				"maxSpeed": 1550
			},
			"movementW": {
				"walk": { "base": 345, "sprint": 796.9 },
				"fly": { "base": 1500, "sprint": 1000 },
				"swim": { "base": 550 }
			},
			"movementD": {
				"walk": { "base": 345, "sprint": 796.9 },
				"fly": { "base": 1500, "sprint": 1000 },
				"swim": { "base": 550 }
			},
			"attack": {
				"defaultDmg": 160,
				"defaultSwingRadius": 1200,
				"attacks": [
					{ "name": "Bite", "interval": 0.5, "dmg": 80, "radius": 495, "stamina": 10 },
					{ "name": "Flame", "interval": 12, "dmg": 0, "radius": 0, "stamina": 20 },
					{ "name": "Grab", "interval": 1, "dmg": 18, "radius": 300, "stamina": 40 },
					{ "name": "Taunt", "interval": 0, "dmg": 60, "radius": 2000, "stamina": 2 },
					{ "name": "Bite (AI)", "interval": 0.5, "dmg": 80, "radius": 614, "stamina": 10 }
				]
			}
		},
		{
			"name": "Fire Wyvern",
			"blueprintPath": "/Game/Mods/SpeedyFlyers/Dinos/Wyvern/Wyvern_Character_BP_Fire.Wyvern_Character_BP_Fire_C",
			"dinoNameTag": "Wyvern",
			"customTag": "Wyvern",
			"targetingTeamName": "Carnivores_High",
			"mass": 800,
			"dragWeight": 555,
			"flags": [
				"allowFlyerLandedRider",
				"allowRiding",
				"canBeDragged",
				"canBeTorpid",
				"canDrag",
				"doStepDamage",
				"isBigDino",
				"isCarnivore",
				"isFlyerDino"
			],
			"falling": {
				"dmgMult": 80,
				"maxSpeed": 1550
			},
			"movementW": {
				"walk": { "base": 345, "sprint": 796.9 },
				"fly": { "base": 1500, "sprint": 1000 },
				"swim": { "base": 550 }
			},
			"movementD": {
				"walk": { "base": 345, "sprint": 796.9 },
				"fly": { "base": 1500, "sprint": 1000 },
				"swim": { "base": 550 }
			},
			"attack": {
				"defaultDmg": 160,
				"defaultSwingRadius": 1200,
				"attacks": [
					{ "name": "Bite", "interval": 0.5, "dmg": 80, "radius": 495, "stamina": 10 },
					{ "name": "Flame", "interval": 5, "dmg": 0, "radius": 0, "stamina": 160 },
					{ "name": "Grab", "interval": 1, "dmg": 18, "radius": 300, "stamina": 40 },
					{ "name": "Taunt", "interval": 0, "dmg": 60, "radius": 2000, "stamina": 2 },
					{ "name": "Bite (AI)", "interval": 0.5, "dmg": 80, "radius": 614, "stamina": 10 }
				]
			}
		},
		{
			"name": "Lightning Wyvern",
			"blueprintPath": "/Game/Mods/SpeedyFlyers/Dinos/Wyvern/Wyvern_Character_BP_Lightning.Wyvern_Character_BP_Lightning_C",
			"dinoNameTag": "Wyvern",
			"customTag": "Wyvern",
			"targetingTeamName": "Carnivores_High",
			"mass": 800,
			"dragWeight": 555,
			"flags": [
				"allowFlyerLandedRider",
				"allowRiding",
				"canBeDragged",
				"canBeTorpid",
				"canDrag",
				"doStepDamage",
				"isBigDino",
				"isCarnivore",
				"isFlyerDino"
			],
			"falling": {
				"dmgMult": 80,
				"maxSpeed": 1550
			},
			"movementW": {
				"walk": { "base": 345, "sprint": 796.9 },
				"fly": { "base": 1500, "sprint": 1000 },
				"swim": { "base": 550 }
			},
			"movementD": {
				"walk": { "base": 345, "sprint": 796.9 },
				"fly": { "base": 1500, "sprint": 1000 },
				"swim": { "base": 550 }
			},
			"attack": {
				"defaultDmg": 160,
				"defaultSwingRadius": 1200,
				"attacks": [
					{ "name": "Bite", "interval": 0.5, "dmg": 80, "radius": 495, "stamina": 10 },
					{
						"name": "Lightning", "interval": 6.5, "dmg": 0, "radius": 0, "stamina": 160,
						"isProjectile": true
					},
					{ "name": "Grab", "interval": 1, "dmg": 18, "radius": 300, "stamina": 40 },
					{ "name": "Taunt", "interval": 0, "dmg": 60, "radius": 2000, "stamina": 2 },
					{ "name": "Bite (AI)", "interval": 0.5, "dmg": 80, "radius": 614, "stamina": 10 }
				]
			}
		},
		{
			"name": "Poison Wyvern",
			"blueprintPath": "/Game/Mods/SpeedyFlyers/Dinos/Wyvern/Wyvern_Character_BP_Poison.Wyvern_Character_BP_Poison_C",
			"dinoNameTag": "Wyvern",
			"customTag": "Wyvern",
			"targetingTeamName": "Carnivores_High",
			"mass": 800,
			"dragWeight": 555,
			"flags": [
				"allowFlyerLandedRider",
				"allowRiding",
				"canBeDragged",
				"canBeTorpid",
				"canDrag",
				"doStepDamage",
				"isBigDino",
				"isCarnivore",
				"isFlyerDino"
			],
			"falling": {
				"dmgMult": 80,
				"maxSpeed": 1550
			},
			"movementW": {
				"walk": { "base": 345, "sprint": 796.9 },
				"fly": { "base": 1500, "sprint": 1000 },
				"swim": { "base": 550 }
			},
			"movementD": {
				"walk": { "base": 345, "sprint": 796.9 },
				"fly": { "base": 1500, "sprint": 1000 },
				"swim": { "base": 550 }
			},
			"attack": {
				"defaultDmg": 160,
				"defaultSwingRadius": 1200,
				"attacks": [
					{ "name": "Bite", "interval": 0.5, "dmg": 80, "radius": 495, "stamina": 10 },
					{
						"name": "Poison (Rider)", "interval": 4, "dmg": 0, "radius": 0, "stamina": 85,
						"isProjectile": true
					},
					{ "name": "Grab", "interval": 1, "dmg": 18, "radius": 300, "stamina": 40 },
					{ "name": "Taunt", "interval": 0, "dmg": 60, "radius": 2000, "stamina": 2 },
					{ "name": "Bite (AI)", "interval": 0.5, "dmg": 80, "radius": 614, "stamina": 10 },
					{
						"name": "Poison (AI)", "interval": 9, "dmg": 0, "radius": 0, "stamina": 20,
						"isProjectile": true
					}
				]
			}
		},
		{
			"name": "Argentavis",
			"blueprintPath": "/Game/Mods/SpeedyFlyers/Dinos_NoOverspawn/Argentavis/Argent_Character_BP_SF.Argent_Character_BP_SF_C",
			"dinoNameTag": "Argent",
			"customTag": "Argent",
			"targetingTeamName": "Carnivores_Medium_TargetPlayerOrTamed",
			"mass": 190,
			"dragWeight": 150,
			"flags": [
				"allowFlyerLandedRider",
				"allowRiding",
				"canBeDragged",
				"canBeTorpid",
				"canDrag",
				"isFlyerDino"
			],
			"falling": {
				"dmgMult": 80,
				"maxSpeed": 1550
			},
			"movementW": {
				"walk": { "base": 140.1, "sprint": 315.3 },
				"fly": { "base": 323.3 },
				"swim": { "base": 161.7 }
			},
			"movementD": {
				"walk": { "base": 260, "sprint": 585 },
				"fly": { "base": 600 },
				"swim": { "base": 300 }
			},
			"attack": {
				"defaultDmg": 25,
				"defaultSwingRadius": 210,
				"attacks": [
					{ "name": "None", "interval": 0.6, "dmg": 25, "radius": 240, "stamina": 0 },
					{ "name": "GrabClaws", "interval": 4, "dmg": 12, "radius": 400, "stamina": 120 },
					{ "name": "GrabBeak", "interval": 4, "dmg": 12, "radius": 300, "stamina": 120 }
				]
			}
		},
		{
			"name": "Corrupted Pteranodon",
			"blueprintPath": "/Game/Mods/SpeedyFlyers/Dinos_NoOverspawn/Corrupt/Ptero/Ptero_Character_BP_Corrupt_SF.Ptero_Character_BP_Corrupt_SF_C",
			"dinoNameTag": "Ptera Corrupt",
			"customTag": "Ptera",
			"targetingTeamName": "Carnivores_High",
			"mass": 190,
			"dragWeight": 149,
			"variants": [ "Corrupted" ],
			"flags": [
				"allowFlyerLandedRider",
				"allowRiding",
				"canBeDragged",
				"canBeTorpid",
				"canDrag",
				"isCarnivore",
				"isCorrupted",
				"isFlyerDino"
			],
			"falling": {
				"dmgMult": 80,
				"maxSpeed": 1550
			},
			"movementW": {
				"walk": { "base": 226.1, "sprint": 715 },
				"fly": { "base": 521.7 },
				"swim": { "base": 260.9 }
			},
			"movementD": {
				"walk": { "base": 260, "sprint": 822.2 },
				"fly": { "base": 600 },
				"swim": { "base": 300 }
			},
			"attack": {
				"defaultDmg": 15,
				"defaultSwingRadius": 200,
				"attacks": [
					{ "name": "None", "interval": 0.6, "dmg": 12, "radius": 200, "stamina": 0 },
					{ "name": "None", "interval": 1, "dmg": 18, "radius": 200, "stamina": 40 },
					{ "name": "Barrel Roll", "interval": 0.6, "dmg": 50, "radius": 260, "stamina": 90 }
				]
			}
		},
		{
			"name": "Corrupted Rock Drake",
			"blueprintPath": "/Game/Mods/SpeedyFlyers/Dinos_NoOverspawn/Corrupt/RockDrake/RockDrake_Character_BP_Corrupt_SF.RockDrake_Character_BP_Corrupt_SF_C",
			"dinoNameTag": "RockDrake Corrupt",
			"customTag": "RockDrake",
			"targetingTeamName": "Carnivores_High",
			"mass": 345,
			"dragWeight": 425,
			"variants": [ "Corrupted" ],
			"flags": [
				"allowMountedWeaponry",
				"allowRiding",
				"canBeDragged",
				"canBeTorpid",
				"doStepDamage",
				"isCarnivore",
				"isCorrupted"
			],
			"falling": {
				"dmgMult": 10,
				"maxSpeed": 1550
			},
			"movementW": {
				"walk": { "base": 520, "sprint": 1820 },
				"swim": { "base": 480 }
			},
			"movementD": {
				"walk": { "base": 585, "sprint": 2047.5 },
				"swim": { "base": 540 }
			},
			"attack": {
				"defaultDmg": 0,
				"defaultSwingRadius": 600,
				"attacks": [
					{ "name": "Bite", "interval": 0.5, "dmg": 60, "radius": 600, "stamina": 20 },
					{ "name": "Toggle Climbing", "interval": 0, "dmg": 0, "radius": 0, "stamina": 0 },
					{ "name": "Toggle Camo", "interval": 0, "dmg": 0, "radius": 0, "stamina": 0 },
					{ "name": "Pounce_DirectHit", "interval": 0, "dmg": 240, "radius": 0, "stamina": 0 },
					{ "name": "Pounce_AOE", "interval": 0, "dmg": 150, "radius": 0, "stamina": 0 },
					{ "name": "Bite (Climbing)", "interval": 0.5, "dmg": 60, "radius": 900, "stamina": 20 }
				]
			}
		},
		{
			"name": "Corrupted Wyvern",
			"blueprintPath": "/Game/Mods/SpeedyFlyers/Dinos_NoOverspawn/Corrupt/Wyvern/Wyvern_Character_BP_Fire_Corrupt_SF.Wyvern_Character_BP_Fire_Corrupt_SF_C",
			"dinoNameTag": "Wyvern",
			"customTag": "Wyvern",
			"targetingTeamName": "Carnivores_High",
			"mass": 800,
			"dragWeight": 555,
			"variants": [ "Corrupted" ],
			"flags": [
				"allowFlyerLandedRider",
				"allowRiding",
				"canBeDragged",
				"canBeTorpid",
				"canDrag",
				"doStepDamage",
				"isBigDino",
				"isCarnivore",
				"isCorrupted",
				"isFlyerDino"
			],
			"falling": {
				"dmgMult": 80,
				"maxSpeed": 1550
			},
			"movementW": {
				"walk": { "base": 345, "sprint": 796.9 },
				"fly": { "base": 1500, "sprint": 1000 },
				"swim": { "base": 550 }
			},
			"movementD": {
				"walk": { "base": 345, "sprint": 796.9 },
				"fly": { "base": 1500, "sprint": 1000 },
				"swim": { "base": 550 }
			},
			"attack": {
				"defaultDmg": 160,
				"defaultSwingRadius": 1200,
				"attacks": [
					{ "name": "Bite", "interval": 0.5, "dmg": 80, "radius": 495, "stamina": 10 },
					{ "name": "Flame", "interval": 5, "dmg": 0, "radius": 0, "stamina": 160 },
					{ "name": "Grab", "interval": 1, "dmg": 18, "radius": 300, "stamina": 40 },
					{ "name": "Taunt", "interval": 0, "dmg": 60, "radius": 2000, "stamina": 2 },
					{ "name": "Bite (AI)", "interval": 0.5, "dmg": 80, "radius": 614, "stamina": 10 }
				]
			}
		},
		{
			"name": "Griffin",
			"blueprintPath": "/Game/Mods/SpeedyFlyers/Dinos_NoOverspawn/Griffin/Griffin_Character_BP_SF.Griffin_Character_BP_SF_C",
			"dinoNameTag": "Griffin",
			"customTag": "Griffin",
			"targetingTeamName": "Carnivores_Medium_Aggressive",
			"mass": 190,
			"dragWeight": 200,
			"flags": [
				"allowFlyerLandedRider",
				"allowMountedWeaponry",
				"allowRiding",
				"canBeDragged",
				"canBeTorpid",
				"canDrag",
				"isBigDino",
				"isCarnivore",
				"isFlyerDino"
			],
			"falling": {
				"dmgMult": 80,
				"maxSpeed": 1550
			},
			"movementW": {
				"walk": { "base": 300, "sprint": 750 },
				"fly": { "base": 750, "sprint": 600 },
				"swim": { "base": 300 }
			},
			"movementD": {
				"walk": { "base": 300, "sprint": 750 },
				"fly": { "base": 750, "sprint": 600 },
				"swim": { "base": 300 }
			},
			"attack": {
				"defaultDmg": 18,
				"defaultSwingRadius": 400,
				"attacks": [
					{ "name": "Claw", "interval": 1, "dmg": 27, "radius": 750, "stamina": 0 },
					{ "name": "Grab", "interval": 1, "dmg": 12, "radius": 500, "stamina": 60 },
					{ "name": "DivingSwipe", "interval": 3, "dmg": 188, "radius": 1500, "stamina": 25 },
					{ "name": "DiveBomb", "interval": 2, "dmg": 115, "radius": 2000, "stamina": 30 }
				]
			}
		},
		{
			"name": "Managarmr",
			"blueprintPath": "/Game/Mods/SpeedyFlyers/Dinos_NoOverspawn/IceJumper/IceJumper_Character_BP_SF.IceJumper_Character_BP_SF_C",
			"dinoNameTag": "Managarmr",
			"customTag": "Managarmr",
			"targetingTeamName": "Carnivores_Medium",
			"mass": 222,
			"dragWeight": 250,
			"flags": [
				"allowRiding",
				"canBeDragged",
				"canBeTorpid",
				"canDrag",
				"isCarnivore"
			],
			"falling": {
				"dmgMult": 40,
				"maxSpeed": 1550
			},
			"movementW": {
				"walk": { "base": 1250, "sprint": 2500 },
				"swim": { "base": 1050 }
			},
			"movementD": {
				"walk": { "base": 1250, "sprint": 2500 },
				"swim": { "base": 1050 }
			},
			"attack": {
				"defaultDmg": 42,
				"defaultSwingRadius": 300,
				"attacks": [
					{ "name": "DashFwd", "interval": 1, "dmg": 10, "radius": 0, "stamina": 0 },
					{
						"name": "IceBreath", "interval": 10, "dmg": 15, "radius": 0, "stamina": 15,
						"isProjectile": true
					},
					{ "name": "Bite", "interval": 1, "dmg": 35, "radius": 300, "stamina": 0 }
				]
			}
		},
		{
			"name": "Lymantria",
			"blueprintPath": "/Game/Mods/SpeedyFlyers/Dinos_NoOverspawn/Moth/Moth_Character_BP_SF.Moth_Character_BP_SF_C",
			"dinoNameTag": "Moth",
			"customTag": "Moth",
			"targetingTeamName": "Herbivores",
			"mass": 190,
			"dragWeight": 149,
			"flags": [
				"allowFlyerLandedRider",
				"allowRiding",
				"canBeDragged",
				"canBeTorpid",
				"canDrag",
				"isFlyerDino"
			],
			"falling": {
				"dmgMult": 80,
				"maxSpeed": 1550
			},
			"movementW": {
				"walk": { "base": 110, "sprint": 220 },
				"fly": { "base": 600 },
				"swim": { "base": 300 }
			},
			"movementD": {
				"walk": { "base": 96.8, "sprint": 193.6 },
				"fly": { "base": 528 },
				"swim": { "base": 264 }
			},
			"attack": {
				"defaultDmg": 15,
				"defaultSwingRadius": 200,
				"attacks": [ { "name": "DropSpores", "interval": 17, "dmg": 18, "radius": 200, "stamina": 50 } ]
			}
		},
		{
			"name": "Snow Owl",
			"blueprintPath": "/Game/Mods/SpeedyFlyers/Dinos_NoOverspawn/Owl/Owl_Character_BP_SF.Owl_Character_BP_SF_C",
			"dinoNameTag": "Owl",
			"customTag": "Owl",
			"targetingTeamName": "",
			"mass": 250,
			"dragWeight": 250,
			"flags": [
				"allowFlyerLandedRider",
				"allowRiding",
				"canBeDragged",
				"canBeTorpid",
				"isFlyerDino",
				"preventCharacterBasing"
			],
			"falling": {
				"dmgMult": 80,
				"maxSpeed": 1550
			},
			"movementW": {
				"walk": { "base": 260, "sprint": 728 },
				"fly": { "base": 600 },
				"swim": { "base": 300 }
			},
			"movementD": {
				"walk": { "base": 260, "sprint": 728 },
				"fly": { "base": 600 },
				"swim": { "base": 300 }
			},
			"attack": {
				"defaultDmg": 15,
				"defaultSwingRadius": 90,
				"attacks": [
					{ "name": "Melee", "interval": 0.6, "dmg": 25, "radius": 240, "stamina": 0 },
					{ "name": "Encapsulate", "interval": 0, "dmg": 0, "radius": 0, "stamina": 0 },
					{ "name": "PredatorVision", "interval": 0, "dmg": 0, "radius": 0, "stamina": 0 }
				]
			}
		},
		{
			"name": "Pelagornis",
			"blueprintPath": "/Game/Mods/SpeedyFlyers/Dinos_NoOverspawn/Pelagornis/Pela_Character_BP_SF.Pela_Character_BP_SF_C",
			"dinoNameTag": "Pela",
			"customTag": "Pela",
			"targetingTeamName": "Herbivores",
			"mass": 190,
			"dragWeight": 120,
			"flags": [
				"allowFlyerLandedRider",
				"allowRiding",
				"canBeDragged",
				"canBeTorpid",
				"canDrag",
				"isFlyerDino"
			],
			"falling": {
				"dmgMult": 80,
				"maxSpeed": 1550
			},
			"movementW": {
				"walk": { "base": 114.8, "sprint": 229.6 },
				"fly": { "base": 521.7 },
				"swim": { "base": 287 }
			},
			"movementD": {
				"walk": { "base": 132, "sprint": 264 },
				"fly": { "base": 600 },
				"swim": { "base": 330 }
			},
			"attack": {
				"defaultDmg": 16,
				"defaultSwingRadius": 170,
				"attacks": [ { "name": "None", "interval": 0.6, "dmg": 16, "radius": 170, "stamina": 0 } ]
			}
		},
		{
			"name": "Phoenix",
			"blueprintPath": "/Game/Mods/SpeedyFlyers/Dinos_NoOverspawn/Phoenix/Phoenix_Character_BP_SF.Phoenix_Character_BP_SF_C",
			"dinoNameTag": "Phoenix",
			"customTag": "Phoenix",
			"targetingTeamName": "Herbivores",
			"mass": 190,
			"dragWeight": 35,
			"flags": [
				"allowRiding",
				"canBeDragged",
				"canDrag",
				"isCarnivore",
				"isFlyerDino"
			],
			"falling": {
				"dmgMult": 80,
				"maxSpeed": 1550
			},
			"movementW": {
				"walk": { "base": 364, "sprint": 637 },
				"fly": { "base": 840 },
				"swim": { "base": 420 }
			},
			"movementD": {
				"walk": { "base": 520, "sprint": 910 },
				"fly": { "base": 1200 },
				"swim": { "base": 600 }
			},
			"attack": {
				"defaultDmg": 14,
				"defaultSwingRadius": 185,
				"attacks": [
					{ "name": "Attack Bite", "interval": 0.6, "dmg": 14, "radius": 350, "stamina": 0 },
					{
						"name": "Fireball (Rider)", "interval": 4, "dmg": 0, "radius": 0, "stamina": 75,
						"isProjectile": true
					},
					{ "name": "Melee Rake", "interval": 1, "dmg": 23, "radius": 350, "stamina": 0 }
				]
			}
		},
		{
			"name": "Pteranodon",
			"blueprintPath": "/Game/Mods/SpeedyFlyers/Dinos_NoOverspawn/Ptero/Ptero_Character_BP_SF.Ptero_Character_BP_SF_C",
			"dinoNameTag": "Ptera",
			"customTag": "Ptera",
			"targetingTeamName": "Herbivores",
			"mass": 190,
			"dragWeight": 149,
			"flags": [
				"allowFlyerLandedRider",
				"allowRiding",
				"canBeDragged",
				"canBeTorpid",
				"canDrag",
				"isFlyerDino"
			],
			"falling": {
				"dmgMult": 80,
				"maxSpeed": 1550
			},
			"movementW": {
				"walk": { "base": 226.1, "sprint": 715 },
				"fly": { "base": 521.7 },
				"swim": { "base": 260.9 }
			},
			"movementD": {
				"walk": { "base": 260, "sprint": 822.2 },
				"fly": { "base": 600 },
				"swim": { "base": 300 }
			},
			"attack": {
				"defaultDmg": 15,
				"defaultSwingRadius": 200,
				"attacks": [
					{ "name": "None", "interval": 0.6, "dmg": 18, "radius": 200, "stamina": 0 },
					{ "name": "None", "interval": 1, "dmg": 18, "radius": 200, "stamina": 40 },
					{ "name": "Barrel Roll", "interval": 0.6, "dmg": 50, "radius": 260, "stamina": 90 }
				]
			}
		},
		{
			"name": "Tek Quetzal",
			"blueprintPath": "/Game/Mods/SpeedyFlyers/Dinos_NoOverspawn/Quetzalcoatlus/BionicQuetz_Character_BP_SF.BionicQuetz_Character_BP_SF_C",
			"dinoNameTag": "Quetz",
			"customTag": "Quetz",
			"targetingTeamName": "Herbivores",
			"mass": 190,
			"dragWeight": 500,
			"flags": [
				"allowFlyerLandedRider",
				"allowRiding",
				"canBeDragged",
				"canBeTorpid",
				"canDrag",
				"isBigDino",
				"isFlyerDino"
			],
			"falling": {
				"dmgMult": 80,
				"maxSpeed": 1550
			},
			"movementW": {
				"walk": { "base": 574.6, "sprint": 1149.1 },
				"fly": { "base": 798 },
				"swim": { "base": 478.8 }
			},
			"movementD": {
				"walk": { "base": 342, "sprint": 684 },
				"fly": { "base": 475 },
				"swim": { "base": 285 }
			},
			"attack": {
				"defaultDmg": 32,
				"defaultSwingRadius": 200,
				"attacks": [
					{ "name": "None", "interval": 0.6, "dmg": 32, "radius": 720, "stamina": 16 },
					{ "name": "None", "interval": 1, "dmg": 32, "radius": 370, "stamina": 80 }
				]
			}
		},
		{
			"name": "Quetzal",
			"blueprintPath": "/Game/Mods/SpeedyFlyers/Dinos_NoOverspawn/Quetzalcoatlus/Quetz_Character_BP_SF.Quetz_Character_BP_SF_C",
			"dinoNameTag": "Quetz",
			"customTag": "Quetz",
			"targetingTeamName": "Herbivores",
			"mass": 190,
			"dragWeight": 500,
			"flags": [
				"allowFlyerLandedRider",
				"allowRiding",
				"canBeDragged",
				"canBeTorpid",
				"canDrag",
				"isBigDino",
				"isFlyerDino"
			],
			"falling": {
				"dmgMult": 80,
				"maxSpeed": 1550
			},
			"movementW": {
				"walk": { "base": 574.6, "sprint": 1149.1 },
				"fly": { "base": 798 },
				"swim": { "base": 478.8 }
			},
			"movementD": {
				"walk": { "base": 342, "sprint": 684 },
				"fly": { "base": 475 },
				"swim": { "base": 285 }
			},
			"attack": {
				"defaultDmg": 32,
				"defaultSwingRadius": 200,
				"attacks": [
					{ "name": "None", "interval": 0.6, "dmg": 32, "radius": 720, "stamina": 16 },
					{ "name": "None", "interval": 1, "dmg": 32, "radius": 370, "stamina": 80 }
				]
			}
		},
		{
			"name": "Rock Drake",
			"blueprintPath": "/Game/Mods/SpeedyFlyers/Dinos_NoOverspawn/RockDrake/RockDrake_Character_BP_SF.RockDrake_Character_BP_SF_C",
			"dinoNameTag": "RockDrake",
			"customTag": "RockDrake",
			"targetingTeamName": "Carnivores_High",
			"mass": 345,
			"dragWeight": 425,
			"flags": [
				"allowMountedWeaponry",
				"allowRiding",
				"canBeDragged",
				"canBeTorpid",
				"doStepDamage",
				"isCarnivore"
			],
			"falling": {
				"dmgMult": 10,
				"maxSpeed": 1550
			},
			"movementW": {
				"walk": { "base": 520, "sprint": 1820 },
				"swim": { "base": 480 }
			},
			"movementD": {
				"walk": { "base": 585, "sprint": 2047.5 },
				"swim": { "base": 540 }
			},
			"attack": {
				"defaultDmg": 0,
				"defaultSwingRadius": 600,
				"attacks": [
					{ "name": "Bite", "interval": 0.5, "dmg": 60, "radius": 600, "stamina": 20 },
					{ "name": "Toggle Climbing", "interval": 0, "dmg": 0, "radius": 0, "stamina": 0 },
					{ "name": "Toggle Camo", "interval": 0, "dmg": 0, "radius": 0, "stamina": 0 },
					{ "name": "Pounce_DirectHit", "interval": 0, "dmg": 240, "radius": 0, "stamina": 0 },
					{ "name": "Pounce_AOE", "interval": 0, "dmg": 150, "radius": 0, "stamina": 0 },
					{ "name": "Bite (Climbing)", "interval": 0.5, "dmg": 60, "radius": 900, "stamina": 20 }
				]
			}
		},
		{
			"name": "Tapejara",
			"blueprintPath": "/Game/Mods/SpeedyFlyers/Dinos_NoOverspawn/Tapejara/Tapejara_Character_BP_SF.Tapejara_Character_BP_SF_C",
			"dinoNameTag": "Tapejara",
			"customTag": "Tapejara",
			"targetingTeamName": "Herbivores_Medium_Aggressive",
			"mass": 190,
			"dragWeight": 149,
			"flags": [
				"allowFlyerLandedRider",
				"allowRiding",
				"canBeDragged",
				"canBeTorpid",
				"canDrag",
				"isFlyerDino"
			],
			"falling": {
				"dmgMult": 80,
				"maxSpeed": 1550
			},
			"movementW": {
				"walk": { "base": 539, "sprint": 862.4 },
				"fly": { "base": 1540 },
				"swim": { "base": 660 }
			},
			"movementD": {
				"walk": { "base": 245, "sprint": 392 },
				"fly": { "base": 700 },
				"swim": { "base": 300 }
			},
			"attack": {
				"defaultDmg": 15,
				"defaultSwingRadius": 200,
				"attacks": [
					{ "name": "Bite", "interval": 0.6, "dmg": 18, "radius": 200, "stamina": 0 },
					{ "name": "Bite II", "interval": 1, "dmg": 18, "radius": 200, "stamina": 40 },
					{ "name": "Taunt", "interval": 0.6, "dmg": 18, "radius": 200, "stamina": 0 }
				]
			}
		},
		{
			"name": "Alpha Fire Wyvern",
			"blueprintPath": "/Game/Mods/SpeedyFlyers/Dinos_NoOverspawn/Wyvern/MegaWyvern_Character_BP_Fire_SF.MegaWyvern_Character_BP_Fire_SF_C",
			"dinoNameTag": "Wyvern",
			"customTag": "Wyvern",
			"targetingTeamName": "Carnivores_High",
			"mass": 800,
			"dragWeight": 555,
			"flags": [
				"allowFlyerLandedRider",
				"allowRiding",
				"canBeDragged",
				"canBeTorpid",
				"canDrag",
				"doStepDamage",
				"isBigDino",
				"isCarnivore",
				"isFlyerDino"
			],
			"falling": {
				"dmgMult": 80,
				"maxSpeed": 1550
			},
			"movementW": {
				"walk": { "base": 345, "sprint": 796.9 },
				"fly": { "base": 1500, "sprint": 1000 },
				"swim": { "base": 550 }
			},
			"movementD": {
				"walk": { "base": 345, "sprint": 796.9 },
				"fly": { "base": 1500, "sprint": 1000 },
				"swim": { "base": 550 }
			},
			"attack": {
				"defaultDmg": 210,
				"defaultSwingRadius": 1200,
				"attacks": [
					{ "name": "Bite", "interval": 0.5, "dmg": 140, "radius": 495, "stamina": 10 },
					{ "name": "Flame", "interval": 5, "dmg": 0, "radius": 0, "stamina": 20 },
					{ "name": "Grab", "interval": 1, "dmg": 18, "radius": 300, "stamina": 40 },
					{ "name": "Taunt", "interval": 0, "dmg": 90, "radius": 2000, "stamina": 2 },
					{ "name": "Bite (AI)", "interval": 0.5, "dmg": 120, "radius": 614, "stamina": 10 }
				]
			}
		},
		{
			"name": "Fire Wyvern",
			"blueprintPath": "/Game/Mods/SpeedyFlyers/Dinos_NoOverspawn/Wyvern/Wyvern_Character_BP_Fire_SF.Wyvern_Character_BP_Fire_SF_C",
			"dinoNameTag": "Wyvern",
			"customTag": "Wyvern",
			"targetingTeamName": "Carnivores_High",
			"mass": 800,
			"dragWeight": 555,
			"flags": [
				"allowFlyerLandedRider",
				"allowRiding",
				"canBeDragged",
				"canBeTorpid",
				"canDrag",
				"doStepDamage",
				"isBigDino",
				"isCarnivore",
				"isFlyerDino"
			],
			"falling": {
				"dmgMult": 80,
				"maxSpeed": 1550
			},
			"movementW": {
				"walk": { "base": 345, "sprint": 796.9 },
				"fly": { "base": 1500, "sprint": 1000 },
				"swim": { "base": 550 }
			},
			"movementD": {
				"walk": { "base": 345, "sprint": 796.9 },
				"fly": { "base": 1500, "sprint": 1000 },
				"swim": { "base": 550 }
			},
			"attack": {
				"defaultDmg": 160,
				"defaultSwingRadius": 1200,
				"attacks": [
					{ "name": "Bite", "interval": 0.5, "dmg": 80, "radius": 495, "stamina": 10 },
					{ "name": "Flame", "interval": 5, "dmg": 0, "radius": 0, "stamina": 160 },
					{ "name": "Grab", "interval": 1, "dmg": 18, "radius": 300, "stamina": 40 },
					{ "name": "Taunt", "interval": 0, "dmg": 60, "radius": 2000, "stamina": 2 },
					{ "name": "Bite (AI)", "interval": 0.5, "dmg": 80, "radius": 614, "stamina": 10 }
				]
			}
		},
		{
			"name": "Ice Wyvern",
			"blueprintPath": "/Game/Mods/SpeedyFlyers/Dinos_NoOverspawn/Wyvern/Wyvern_Character_BP_Ice_SF.Wyvern_Character_BP_Ice_SF_C",
			"dinoNameTag": "Wyvern",
			"customTag": "Wyvern",
			"targetingTeamName": "Carnivores_High",
			"mass": 800,
			"dragWeight": 555,
			"flags": [
				"allowFlyerLandedRider",
				"allowRiding",
				"canBeDragged",
				"canBeTorpid",
				"canDrag",
				"doStepDamage",
				"isBigDino",
				"isCarnivore",
				"isFlyerDino"
			],
			"falling": {
				"dmgMult": 80,
				"maxSpeed": 1550
			},
			"movementW": {
				"walk": { "base": 345, "sprint": 796.9 },
				"fly": { "base": 1500, "sprint": 1000 },
				"swim": { "base": 550 }
			},
			"movementD": {
				"walk": { "base": 345, "sprint": 796.9 },
				"fly": { "base": 1500, "sprint": 1000 },
				"swim": { "base": 550 }
			},
			"attack": {
				"defaultDmg": 160,
				"defaultSwingRadius": 1200,
				"attacks": [
					{ "name": "Bite", "interval": 0.5, "dmg": 80, "radius": 495, "stamina": 10 },
					{ "name": "Flame", "interval": 5, "dmg": 0, "radius": 0, "stamina": 160 },
					{ "name": "Grab", "interval": 1, "dmg": 18, "radius": 300, "stamina": 40 },
					{ "name": "Taunt", "interval": 0, "dmg": 60, "radius": 2000, "stamina": 2 },
					{ "name": "Bite (AI)", "interval": 0.5, "dmg": 80, "radius": 614, "stamina": 10 }
				]
			}
		},
		{
			"name": "Lightning Wyvern",
			"blueprintPath": "/Game/Mods/SpeedyFlyers/Dinos_NoOverspawn/Wyvern/Wyvern_Character_BP_Lightning_SF.Wyvern_Character_BP_Lightning_SF_C",
			"dinoNameTag": "Wyvern",
			"customTag": "Wyvern",
			"targetingTeamName": "Carnivores_High",
			"mass": 800,
			"dragWeight": 555,
			"flags": [
				"allowFlyerLandedRider",
				"allowRiding",
				"canBeDragged",
				"canBeTorpid",
				"canDrag",
				"doStepDamage",
				"isBigDino",
				"isCarnivore",
				"isFlyerDino"
			],
			"falling": {
				"dmgMult": 80,
				"maxSpeed": 1550
			},
			"movementW": {
				"walk": { "base": 345, "sprint": 796.9 },
				"fly": { "base": 1500, "sprint": 1000 },
				"swim": { "base": 550 }
			},
			"movementD": {
				"walk": { "base": 345, "sprint": 796.9 },
				"fly": { "base": 1500, "sprint": 1000 },
				"swim": { "base": 550 }
			},
			"attack": {
				"defaultDmg": 160,
				"defaultSwingRadius": 1200,
				"attacks": [
					{ "name": "Bite", "interval": 0.5, "dmg": 80, "radius": 495, "stamina": 10 },
					{
						"name": "Lightning", "interval": 6.5, "dmg": 0, "radius": 0, "stamina": 160,
						"isProjectile": true
					},
					{ "name": "Grab", "interval": 1, "dmg": 18, "radius": 300, "stamina": 40 },
					{ "name": "Taunt", "interval": 0, "dmg": 60, "radius": 2000, "stamina": 2 },
					{ "name": "Bite (AI)", "interval": 0.5, "dmg": 80, "radius": 614, "stamina": 10 }
				]
			}
		},
		{
			"name": "Poison Wyvern",
			"blueprintPath": "/Game/Mods/SpeedyFlyers/Dinos_NoOverspawn/Wyvern/Wyvern_Character_BP_Poison_SF.Wyvern_Character_BP_Poison_SF_C",
			"dinoNameTag": "Wyvern",
			"customTag": "Wyvern",
			"targetingTeamName": "Carnivores_High",
			"mass": 800,
			"dragWeight": 555,
			"flags": [
				"allowFlyerLandedRider",
				"allowRiding",
				"canBeDragged",
				"canBeTorpid",
				"canDrag",
				"doStepDamage",
				"isBigDino",
				"isCarnivore",
				"isFlyerDino"
			],
			"falling": {
				"dmgMult": 80,
				"maxSpeed": 1550
			},
			"movementW": {
				"walk": { "base": 345, "sprint": 796.9 },
				"fly": { "base": 1500, "sprint": 1000 },
				"swim": { "base": 550 }
			},
			"movementD": {
				"walk": { "base": 345, "sprint": 796.9 },
				"fly": { "base": 1500, "sprint": 1000 },
				"swim": { "base": 550 }
			},
			"attack": {
				"defaultDmg": 160,
				"defaultSwingRadius": 1200,
				"attacks": [
					{ "name": "Bite", "interval": 0.5, "dmg": 80, "radius": 495, "stamina": 10 },
					{
						"name": "Poison (Rider)", "interval": 4, "dmg": 0, "radius": 0, "stamina": 85,
						"isProjectile": true
					},
					{ "name": "Grab", "interval": 1, "dmg": 18, "radius": 300, "stamina": 40 },
					{ "name": "Taunt", "interval": 0, "dmg": 60, "radius": 2000, "stamina": 2 },
					{ "name": "Bite (AI)", "interval": 0.5, "dmg": 80, "radius": 614, "stamina": 10 },
					{
						"name": "Poison (AI)", "interval": 9, "dmg": 0, "radius": 0, "stamina": 20,
						"isProjectile": true
					}
				]
			}
		}
	]
}